Workbook
Name Tabela10: #REF!

Sheet Tabela de Natureza Jurídica 
A1: Código | B1: Natureza Jurídica | C1: Categoria | D1: Integrantes do Quadro de Sócios e Administradores (QSA)
A2: 101-5 | B2: Órgão Público do Poder Executivo Federal | C2: Administração pública | D2: Administrador
A3: 102-3 | B3: Órgão Público do Poder Executivo Estadual ou do Distrito Federal | C3: Administração pública | D3: Administrador
A4: 103-1 | B4: Órgão Público do Poder Executivo Municipal | C4: Administração pública | D4: Administrador
A5: 104-0 | B5: Órgão Público do Poder Legislativo Federal | C5: Administração pública | D5: Administrador
A6: 105-8 | B6: Órgão Público do Poder Legislativo Estadual ou do Distrito Federal | C6: Administração pública | D6: Administrador
A7: 106-6 | B7: Órgão Público do Poder Legislativo Municipal | C7: Administração pública | D7: Administrador
A8: 107-4 | B8: Órgão Público do Poder Judiciário Federal | C8: Administração pública | D8: Administrador
A9: 108-2 | B9: Órgão Público do Poder Judiciário Estadual | C9: Administração pública | D9: Administrador
A10: 110-4 | B10: Autarquia Federal | C10: Administração pública | D10: Administrador ou Presidente
A11: 111-2 | B11: Autarquia Estadual ou do Distrito Federal | C11: Administração pública | D11: Administrador ou Presidente
A12: 112-0 | B12: Autarquia Municipal | C12: Administração pública | D12: Administrador ou Presidente
... A83: 503-7 | B83: Outras Instituições Extraterritoriais | C83: Organizações internacionais e outras instituições extraterritorial | D83: Representante da Instituição Extraterritorial

Sheet CNAE_Cód.Atividade Econômica
A1: CNAE | B1: Descrição | C1: Atividade Econômica
A2: 161-0/03 | B2: Serviço de preparação de terreno, cultivo e colheita | C2: =CÓDIGO_CNAE[[#This Row],[CNAE]] & " - " & CÓDIGO_CNAE[[#This Row],[Descrição]] -> 161-0/03 - Serviço de preparação de terreno, cultivo e colheita
A3: 162-8/03 | B3: Serviço de manejo de animais | C3: =CÓDIGO_CNAE[[#This Row],[CNAE]] & " - " & CÓDIGO_CNAE[[#This Row],[Descrição]] -> 162-8/03 - Serviço de manejo de animais
A4: 322-1/07 | B4: Atividades de apoio à aqüicultura em água doce | C4: =CÓDIGO_CNAE[[#This Row],[CNAE]] & " - " & CÓDIGO_CNAE[[#This Row],[Descrição]] -> 322-1/07 - Atividades de apoio à aqüicultura em água doce
A5: 1099-6/04 | B5: Fabricação de gelo comum | C5: =CÓDIGO_CNAE[[#This Row],[CNAE]] & " - " & CÓDIGO_CNAE[[#This Row],[Descrição]] -> 1099-6/04 - Fabricação de gelo comum
A6: 3250-7/06 | B6: Serviços de prótese dentária | C6: =CÓDIGO_CNAE[[#This Row],[CNAE]] & " - " & CÓDIGO_CNAE[[#This Row],[Descrição]] -> 3250-7/06 - Serviços de prótese dentária
A7: 3250-7/09 | B7: Serviço de laboratório óptico | C7: =CÓDIGO_CNAE[[#This Row],[CNAE]] & " - " & CÓDIGO_CNAE[[#This Row],[Descrição]] -> 3250-7/09 - Serviço de laboratório óptico
A8: 3312-1/02 | B8: Manutenção e reparação de aparelhos e instrumentos de medida, teste e controle | C8: =CÓDIGO_CNAE[[#This Row],[CNAE]] & " - " & CÓDIGO_CNAE[[#This Row],[Descrição]] -> 3312-1/02 - Manutenção e reparação de aparelhos e instrumentos de medida, teste e controle
A9: 3312-1/03 | B9: Manutenção e reparação de aparelhos eletromédicos e eletroterapêuticos e equipamentos de irradiação | C9: =CÓDIGO_CNAE[[#This Row],[CNAE]] & " - " & CÓDIGO_CNAE[[#This Row],[Descrição]] -> 3312-1/03 - Manutenção e reparação de aparelhos eletromédicos e eletroterapêuticos e equipamentos de irradiação
A10: 3312-1/04 | B10: Manutenção e reparação de equipamentos e instrumentos ópticos | C10: =CÓDIGO_CNAE[[#This Row],[CNAE]] & " - " & CÓDIGO_CNAE[[#This Row],[Descrição]] -> 3312-1/04 - Manutenção e reparação de equipamentos e instrumentos ópticos
A11: 3313-9/01 | B11: Manutenção e reparação de geradores, transformadores e motores elétricos | C11: =CÓDIGO_CNAE[[#This Row],[CNAE]] & " - " & CÓDIGO_CNAE[[#This Row],[Descrição]] -> 3313-9/01 - Manutenção e reparação de geradores, transformadores e motores elétricos
A12: 3313-9/02 | B12: Manutenção e reparação de baterias e acumuladores elétricos, exceto para veículos | C12: =CÓDIGO_CNAE[[#This Row],[CNAE]] & " - " & CÓDIGO_CNAE[[#This Row],[Descrição]] -> 3313-9/02 - Manutenção e reparação de baterias e acumuladores elétricos, exceto para veículos
A13: 3313-9/99 | B13: Manutenção e reparação de máquinas, aparelhos e materiais elétricos não especificados anteriormente | C13: =CÓDIGO_CNAE[[#This Row],[CNAE]] & " - " & CÓDIGO_CNAE[[#This Row],[Descrição]] -> 3313-9/99 - Manutenção e reparação de máquinas, aparelhos e materiais elétricos não especificados anteriormente
... A392: 9609-2/99 | B392: Outras atividades de serviços pessoais não especificadas anteriormente | C392: =CÓDIGO_CNAE[[#This Row],[CNAE]] & " - " & CÓDIGO_CNAE[[#This Row],[Descrição]] -> 9609-2/99 - Outras atividades de serviços pessoais não especificadas anteriormente

Sheet TAB.AUXILIAR
B5: VENDEDORES | C5: Percentual de Consultas por Solicitante – Setor de Vendas | F5: Pontuação para Empresas (CNPJ) e Pessoa Física (PF)
B6: Maria | C6: =COUNTIF('CONTROLE DIÁRIO DE CONSULTAS'!$I$10:$I$1048576,TAB.AUXILIAR!B5:B6) -> 1 | F6: MEI (Microempreendedor Individual): | G6: Pontuação 70-80, pois normalmente são negócios pequenos com menor risco, mas dependem da saúde financeira do empreendedor.
B7: José | C7: =COUNTIF('CONTROLE DIÁRIO DE CONSULTAS'!$I$10:$I$1048576,TAB.AUXILIAR!B6:B7) -> 5 | F7: ME (Microempresa): | G7: Pontuação 80-90, um pouco mais estruturada e com maior estabilidade financeira.
B8: João | C8: =COUNTIF('CONTROLE DIÁRIO DE CONSULTAS'!$I$10:$I$1048576,TAB.AUXILIAR!B7:B8) -> 3 | F8: EPP (Empresa de Pequeno Porte): | G8: Pontuação 90-95, empresas maiores têm mais estabilidade, porém ainda apresentam algum risco.
B9: Carla | C9: =COUNTIF('CONTROLE DIÁRIO DE CONSULTAS'!$I$10:$I$1048576,TAB.AUXILIAR!B8:B9) -> 14 | F9: LTDA (Sociedade Limitada): | G9: Pontuação 95-100, empresas com boa estrutura e capacidade de gestão financeira.
B10: Larissa | C10: =COUNTIF('CONTROLE DIÁRIO DE CONSULTAS'!$I$10:$I$1048576,TAB.AUXILIAR!B9:B10) -> 3 | F10: S/A (Sociedade Anônima): | G10: Pontuação 100, empresas grandes e com boa reputação no mercado.
B12: SEGMENTO DA INCLUSÃO | F12: Faixa de Pontuação e Classificação de Risco (serasa)
B13: LOJA | F13: Pontuação (0 a 1000) | G13: Classificação de Risco | H13: Descrição
B14: TELEFONIA | F14: 901 - 1000 | G14: Baixo | H14: Risco muito baixo de inadimplência.
B15: OUTROS | F15: 701 - 900 | G15: Médio-Baixo | H15: Risco moderado, mas com boa chance de pagamento.
F16: 501 - 700 | G16: Médio | H16: Risco médio, possibilidade de inadimplência.
B17: STATUS DE APROVAÇÃO | F17: 301 - 500 | G17: Médio-Alto | H17: Risco elevado de inadimplência.
B18: Aprovado | F18: 0 - 300 | G18: Alto | H18: Risco muito alto, grande chance de inadimplência.
B19: Reprovado
B20: Em Análise | F20: Para Pessoa Física (PF)
F21: Pontuação de Crédito no Serasa
B22: SETORES | F22: 300 → Risco Alto (alta chance de inadimplência)
B23: Departamento de Crédito/Análise de Crédito | F23: 301 a 500 → Risco Médio (risco moderado de inadimplência)
B24: Departamento de Cobrança | F24: 501 a 700 → Bom (risco baixo, mas ainda pode melhorar)
B25: Financeiro (Contas a Receber) | F25: 701 a 1000 → Muito Bom (ótima reputação financeira, alta chance de crédito aprovado)
B26: Jurídico
B27: Vendas
B28: Direção

Sheet CONTROLE DIÁRIO DE CONSULTAS
A1: CONTROLE DIÁRIO DE CONSULTAS
D5: DATA ATUAL | N5: Aprovado | O5: =COUNTIF(A:K,N5) -> 20
N6: Reprovado | O6: =COUNTIF(A:K,N6) -> 1
D7: =TODAY() -> 45738 | N7: Em Análise | O7: =COUNTIF(A:K,N7) -> 5
D9: DATA DE CONSULTA | E9: EMPRESA / CLIENTE | F9: CNPJ / CPF | G9: CLASSIFICAÇÃO | H9: DESCRIÇÃO DA ATIVIDADE ECONÔMICA (SETOR) | I9: SOLICITAÇÃO | J9: SETOR SOLICITANTE | K9: Status de Aprovação | M9: Mês | N9: Setor | O9: Setor | Q9: Setor | R9: Quantidade | U9: auxiliar01 | V9: auxiliar02 | Y9: RANKING | AB9: AUX01 | AC9: auxiliar02
D10: 45293 | E10: EMPRESA A | F10: 00.111.222/0001-00 | G10: EPP (Empresa de Pequeno Porte) | H10: 4783-1/02 - Comércio varejista de artigos de relojoaria | I10: Maria | J10: Vendas | K10: Reprovado | M10: =IF(ISBLANK(D10), "", IFERROR(PROPER(TEXT(D10,"mmmm")),"")) -> Janeiro | N10: =H10 -> 4783-1/02 - Comércio varejista de artigos de relojoaria | O10: =IFERROR(RIGHT(N10,LEN(N10)-SEARCH("- ",N10)-1),"") -> Comércio varejista de artigos de relojoaria | Q10: ='CNAE_Cód.Atividade Econômica'!B152 -> Comércio varejista de plantas e flores naturais | R10: =COUNTIF($O:$O,Q10) -> 8 | S10: =Q10 -> Comércio varejista de plantas e flores naturais | U10: =COUNTIF(R$10:R10,R10) -> 1 | V10: =R10&U10 -> 81 | W10: =INDEX($S$10:$S$401, MATCH(V10,$V$10:$V$1048576, 0)) -> Comércio varejista de plantas e flores naturais | Y10: 1 | Z10: =LARGE($R$10:$R$1048576,Y10) -> 8 | AA10: =INDEX(S$10:S$1000, MATCH(R10, R$10:R$1000, 0)) -> Comércio varejista de plantas e flores naturais | AB10: =COUNTIF(R$10:R10,R10) -> 1 | AC10: =R10&U10 -> 81 | AD10: =INDEX($S$10:$S$1048576, MATCH(AC10, $V$10:$V$1048576, 0)) -> Comércio varejista de plantas e flores naturais | AE10: =Z10 -> 8
D11: 45293 | E11: EMPRESA B | F11: 00.111.222/0001-01 | G11: ME (Microempresa) | H11: 4783-1/02 - Comércio varejista de artigos de relojoaria | I11: José | J11: Vendas | K11: Aprovado | M11: =IF(ISBLANK(D11), "", IFERROR(PROPER(TEXT(D11,"mmmm")),"")) -> Janeiro | N11: =H11 -> 4783-1/02 - Comércio varejista de artigos de relojoaria | O11: =IFERROR(RIGHT(N11,LEN(N11)-SEARCH("- ",N11)-1),"") -> Comércio varejista de artigos de relojoaria | Q11: ='CNAE_Cód.Atividade Econômica'!B149 -> Comércio varejista de antigüidades | R11: =COUNTIF($O:$O,Q11) -> 7 | S11: =Q11 -> Comércio varejista de antigüidades | U11: =COUNTIF(R$10:R11,R11) -> 1 | V11: =R11&U11 -> 71 | W11: =INDEX($S$10:$S$401, MATCH(V11,$V$10:$V$1048576, 0)) -> Comércio varejista de antigüidades | Y11: 2 | Z11: =LARGE($R$10:$R$1048576,Y11) -> 7 | AA11: =INDEX(S$10:S$1000, MATCH(R11, R$10:R$1000, 0)) -> Comércio varejista de antigüidades | AB11: =COUNTIF(R$10:R11,R11) -> 1 | AC11: =R11&U11 -> 71 | AD11: =INDEX($S$10:$S$1048576, MATCH(AC11, $V$10:$V$1048576, 0)) -> Comércio varejista de antigüidades | AE11: =Z11 -> 7
D12: 45293 | E12: EMPRESA C | F12: 00.111.222/0001-02 | G12: S/A (Sociedade Anônima) | H12: 4789-0/02 - Comércio varejista de plantas e flores naturais | I12: José | J12: Vendas | K12: Em Análise | M12: =IF(ISBLANK(D12), "", IFERROR(PROPER(TEXT(D12,"mmmm")),"")) -> Janeiro | N12: =H12 -> 4789-0/02 - Comércio varejista de plantas e flores naturais | O12: =IFERROR(RIGHT(N12,LEN(N12)-SEARCH("- ",N12)-1),"") -> Comércio varejista de plantas e flores naturais | Q12: ='CNAE_Cód.Atividade Econômica'!B148 -> Comércio varejista de artigos de relojoaria | R12: =COUNTIF($O:$O,Q12) -> 4 | S12: =Q12 -> Comércio varejista de artigos de relojoaria | U12: =COUNTIF(R$10:R12,R12) -> 1 | V12: =R12&U12 -> 41 | W12: =INDEX($S$10:$S$401, MATCH(V12,$V$10:$V$1048576, 0)) -> Comércio varejista de artigos de relojoaria | Y12: 3 | Z12: =LARGE($R$10:$R$1048576,Y12) -> 4 | AA12: =INDEX(S$10:S$1000, MATCH(R12, R$10:R$1000, 0)) -> Comércio varejista de artigos de relojoaria | AB12: =COUNTIF(R$10:R12,R12) -> 1 | AC12: =R12&U12 -> 41 | AD12: =INDEX($S$10:$S$1048576, MATCH(AC12, $V$10:$V$1048576, 0)) -> Comércio varejista de artigos de relojoaria | AE12: =Z12 -> 4
D13: 45294 | E13: EMPRESA D | F13: 00.111.222/0001-03 | G13: S/A (Sociedade Anônima) | H13: 4789-0/02 - Comércio varejista de plantas e flores naturais | I13: José | J13: Vendas | K13: Aprovado | M13: =IF(ISBLANK(D13), "", IFERROR(PROPER(TEXT(D13,"mmmm")),"")) -> Janeiro | N13: =H13 -> 4789-0/02 - Comércio varejista de plantas e flores naturais | O13: =IFERROR(RIGHT(N13,LEN(N13)-SEARCH("- ",N13)-1),"") -> Comércio varejista de plantas e flores naturais | Q13: ='CNAE_Cód.Atividade Econômica'!B68 -> Serviços de capotaria | R13: =COUNTIF($O:$O,Q13) -> 2 | S13: =Q13 -> Serviços de capotaria | U13: =COUNTIF(R$10:R13,R13) -> 1 | V13: =R13&U13 -> 21 | W13: =INDEX($S$10:$S$401, MATCH(V13,$V$10:$V$1048576, 0)) -> Serviços de capotaria | Y13: 4 | Z13: =LARGE($R$10:$R$1048576,Y13) -> 2 | AA13: =INDEX(S$10:S$1000, MATCH(R13, R$10:R$1000, 0)) -> Serviços de capotaria | AB13: =COUNTIF(R$10:R13,R13) -> 1 | AC13: =R13&U13 -> 21 | AD13: =INDEX($S$10:$S$1048576, MATCH(AC13, $V$10:$V$1048576, 0)) -> Serviços de capotaria | AE13: =Z13 -> 2
D14: 45323 | E14: EMPRESA E | F14: 00.111.222/0001-04 | G14: MEI (Microempreendedor Individual) | H14: 4789-0/02 - Comércio varejista de plantas e flores naturais | I14: José | J14: Vendas | K14: Aprovado | M14: =IF(ISBLANK(D14), "", IFERROR(PROPER(TEXT(D14,"mmmm")),"")) -> Fevereiro | N14: =H14 -> 4789-0/02 - Comércio varejista de plantas e flores naturais | O14: =IFERROR(RIGHT(N14,LEN(N14)-SEARCH("- ",N14)-1),"") -> Comércio varejista de plantas e flores naturais | Q14: ='CNAE_Cód.Atividade Econômica'!B167 -> Campings | R14: =COUNTIF($O:$O,Q14) -> 2 | S14: =Q14 -> Campings | U14: =COUNTIF(R$10:R14,R14) -> 2 | V14: =R14&U14 -> 22 | W14: =INDEX($S$10:$S$401, MATCH(V14,$V$10:$V$1048576, 0)) -> Campings | Y14: 5 | Z14: =LARGE($R$10:$R$1048576,Y14) -> 2 | AA14: =INDEX(S$10:S$1000, MATCH(R14, R$10:R$1000, 0)) -> Serviços de capotaria | AB14: =COUNTIF(R$10:R14,R14) -> 2 | AC14: =R14&U14 -> 22 | AD14: =INDEX($S$10:$S$1048576, MATCH(AC14, $V$10:$V$1048576, 0)) -> Campings | AE14: =Z14 -> 2
D15: 45323 | E15: EMPRESA F | F15: 00.111.222/0001-05 | G15: MEI (Microempreendedor Individual) | H15: 4789-0/02 - Comércio varejista de plantas e flores naturais | I15: José | J15: Vendas | K15: Aprovado | M15: =IF(ISBLANK(D15), "", IFERROR(PROPER(TEXT(D15,"mmmm")),"")) -> Fevereiro | N15: =H15 -> 4789-0/02 - Comércio varejista de plantas e flores naturais | O15: =IFERROR(RIGHT(N15,LEN(N15)-SEARCH("- ",N15)-1),"") -> Comércio varejista de plantas e flores naturais | Q15: ='CNAE_Cód.Atividade Econômica'!B160 -> Guarda-móveis | R15: =COUNTIF($O:$O,Q15) -> 0 | S15: =Q15 -> Guarda-móveis | U15: =COUNTIF(R$10:R15,R15) -> 1 | V15: =R15&U15 -> 01 | W15: =INDEX($S$10:$S$401, MATCH(V15,$V$10:$V$1048576, 0)) -> Guarda-móveis | Y15: 6 | Z15: =LARGE($R$10:$R$1048576,Y15) -> 1 | AA15: =INDEX(S$10:S$1000, MATCH(R15, R$10:R$1000, 0)) -> Guarda-móveis | AB15: =COUNTIF(R$10:R15,R15) -> 1 | AC15: =R15&U15 -> 01 | AD15: =INDEX($S$10:$S$1048576, MATCH(AC15, $V$10:$V$1048576, 0)) -> Guarda-móveis | AE15: =Z15 -> 1
D16: 45323 | E16: EMPRESA G | F16: 00.111.222/0001-06 | G16: MEI (Microempreendedor Individual) | H16: 4789-0/02 - Comércio varejista de plantas e flores naturais | I16: João | J16: Vendas | K16: Aprovado | M16: =IF(ISBLANK(D16), "", IFERROR(PROPER(TEXT(D16,"mmmm")),"")) -> Fevereiro | N16: =H16 -> 4789-0/02 - Comércio varejista de plantas e flores naturais | O16: =IFERROR(RIGHT(N16,LEN(N16)-SEARCH("- ",N16)-1),"") -> Comércio varejista de plantas e flores naturais | Q16: ='CNAE_Cód.Atividade Econômica'!B150 -> Comércio varejista de outros artigos usados | R16: =COUNTIF($O:$O,Q16) -> 1 | S16: =Q16 -> Comércio varejista de outros artigos usados | U16: =COUNTIF(R$10:R16,R16) -> 1 | V16: =R16&U16 -> 11 | W16: =INDEX($S$10:$S$401, MATCH(V16,$V$10:$V$1048576, 0)) -> Comércio varejista de outros artigos usados | Y16: 7 | Z16: =LARGE($R$10:$R$1048576,Y16) -> 1 | AA16: =INDEX(S$10:S$1000, MATCH(R16, R$10:R$1000, 0)) -> Comércio varejista de outros artigos usados | AB16: =COUNTIF(R$10:R16,R16) -> 1 | AC16: =R16&U16 -> 11 | AD16: =INDEX($S$10:$S$1048576, MATCH(AC16, $V$10:$V$1048576, 0)) -> Comércio varejista de outros artigos usados | AE16: =Z16 -> 1
D17: 45323 | E17: EMPRESA H | F17: 00.111.222/0001-07 | G17: MEI (Microempreendedor Individual) | H17: 4789-0/02 - Comércio varejista de plantas e flores naturais | I17: João | J17: Vendas | K17: Aprovado | M17: =IF(ISBLANK(D17), "", IFERROR(PROPER(TEXT(D17,"mmmm")),"")) -> Fevereiro | N17: =H17 -> 4789-0/02 - Comércio varejista de plantas e flores naturais | O17: =IFERROR(RIGHT(N17,LEN(N17)-SEARCH("- ",N17)-1),"") -> Comércio varejista de plantas e flores naturais | Q17: ='CNAE_Cód.Atividade Econômica'!B151 -> Comércio varejista de suvenires, bijuterias e artesanatos | R17: =COUNTIF($O:$O,Q17) -> 1 | S17: =Q17 -> Comércio varejista de suvenires, bijuterias e artesanatos | U17: =COUNTIF(R$10:R17,R17) -> 2 | V17: =R17&U17 -> 12 | W17: =INDEX($S$10:$S$401, MATCH(V17,$V$10:$V$1048576, 0)) -> Comércio varejista de suvenires, bijuterias e artesanatos | Y17: 8 | Z17: =LARGE($R$10:$R$1048576,Y17) -> 1 | AA17: =INDEX(S$10:S$1000, MATCH(R17, R$10:R$1000, 0)) -> Comércio varejista de outros artigos usados | AB17: =COUNTIF(R$10:R17,R17) -> 2 | AC17: =R17&U17 -> 12 | AD17: =INDEX($S$10:$S$1048576, MATCH(AC17, $V$10:$V$1048576, 0)) -> Comércio varejista de suvenires, bijuterias e artesanatos | AE17: =Z17 -> 1
D18: 45323 | E18: EMPRESA I | F18: 00.111.222/0001-08 | G18: MEI (Microempreendedor Individual) | H18: 4789-0/02 - Comércio varejista de plantas e flores naturais | I18: João | J18: Vendas | K18: Aprovado | M18: =IF(ISBLANK(D18), "", IFERROR(PROPER(TEXT(D18,"mmmm")),"")) -> Fevereiro | N18: =H18 -> 4789-0/02 - Comércio varejista de plantas e flores naturais | O18: =IFERROR(RIGHT(N18,LEN(N18)-SEARCH("- ",N18)-1),"") -> Comércio varejista de plantas e flores naturais | Q18: ='CNAE_Cód.Atividade Econômica'!B153 -> Comércio varejista de objetos de arte | R18: =COUNTIF($O:$O,Q18) -> 1 | S18: =Q18 -> Comércio varejista de objetos de arte | U18: =COUNTIF(R$10:R18,R18) -> 3 | V18: =R18&U18 -> 13 | W18: =INDEX($S$10:$S$401, MATCH(V18,$V$10:$V$1048576, 0)) -> Comércio varejista de objetos de arte | Y18: 9 | Z18: =LARGE($R$10:$R$1048576,Y18) -> 0 | AA18: =INDEX(S$10:S$1000, MATCH(R18, R$10:R$1000, 0)) -> Comércio varejista de outros artigos usados | AB18: =COUNTIF(R$10:R18,R18) -> 3 | AC18: =R18&U18 -> 13 | AD18: =INDEX($S$10:$S$1048576, MATCH(AC18, $V$10:$V$1048576, 0)) -> Comércio varejista de objetos de arte | AE18: =Z18 -> 0
D19: 45356 | E19: EMPRESA J | F19: 00.111.222/0001-09 | G19: EPP (Empresa de Pequeno Porte) | H19: 4785-7/99 - Comércio varejista de outros artigos usados | I19: Larissa | J19: Vendas | K19: Aprovado | M19: =IF(ISBLANK(D19), "", IFERROR(PROPER(TEXT(D19,"mmmm")),"")) -> Março | N19: =H19 -> 4785-7/99 - Comércio varejista de outros artigos usados | O19: =IFERROR(RIGHT(N19,LEN(N19)-SEARCH("- ",N19)-1),"") -> Comércio varejista de outros artigos usados | Q19: ='CNAE_Cód.Atividade Econômica'!B2 -> Serviço de preparação de terreno, cultivo e colheita | R19: =COUNTIF($O:$O,Q19) -> 0 | S19: =Q19 -> Serviço de preparação de terreno, cultivo e colheita | U19: =COUNTIF(R$10:R19,R19) -> 2 | V19: =R19&U19 -> 02 | W19: =INDEX($S$10:$S$401, MATCH(V19,$V$10:$V$1048576, 0)) -> Serviço de preparação de terreno, cultivo e colheita | Y19: 10 | Z19: =LARGE($R$10:$R$1048576,Y19) -> 0 | AA19: =INDEX(S$10:S$1000, MATCH(R19, R$10:R$1000, 0)) -> Guarda-móveis | AB19: =COUNTIF(R$10:R19,R19) -> 2 | AC19: =R19&U19 -> 02 | AD19: =INDEX($S$10:$S$1048576, MATCH(AC19, $V$10:$V$1048576, 0)) -> Serviço de preparação de terreno, cultivo e colheita | AE19: =Z19 -> 0
D20: 45356 | E20: EMPRESA K | F20: 00.111.222/0001-10 | G20: EPP (Empresa de Pequeno Porte) | H20: 5590-6/02 - Campings | I20: Larissa | J20: Vendas | K20: Aprovado | M20: =IF(ISBLANK(D20), "", IFERROR(PROPER(TEXT(D20,"mmmm")),"")) -> Março | N20: =H20 -> 5590-6/02 - Campings | O20: =IFERROR(RIGHT(N20,LEN(N20)-SEARCH("- ",N20)-1),"") -> Campings | Q20: ='CNAE_Cód.Atividade Econômica'!B386 -> Atividades de Estética e outros serviços de cuidados com a beleza | R20: =COUNTIF($O:$O,Q20) -> 0 | S20: =Q20 -> Atividades de Estética e outros serviços de cuidados com a beleza | U20: =COUNTIF(R$10:R20,R20) -> 3 | V20: =R20&U20 -> 03 | W20: =INDEX($S$10:$S$401, MATCH(V20,$V$10:$V$1048576, 0)) -> Atividades de Estética e outros serviços de cuidados com a beleza | Y20: 11 | Z20: =LARGE($R$10:$R$1048576,Y20) -> 0 | AA20: =INDEX(S$10:S$1000, MATCH(R20, R$10:R$1000, 0)) -> Guarda-móveis | AB20: =COUNTIF(R$10:R20,R20) -> 3 | AC20: =R20&U20 -> 03 | AD20: =INDEX($S$10:$S$1048576, MATCH(AC20, $V$10:$V$1048576, 0)) -> Atividades de Estética e outros serviços de cuidados com a beleza | AE20: =Z20 -> 0
D21: 45383 | E21: EMPRESA L | F21: 00.111.222/0001-11 | G21: EPP (Empresa de Pequeno Porte) | H21: 4789-0/01 - Comércio varejista de suvenires, bijuterias e artesanatos | I21: Larissa | J21: Vendas | K21: Aprovado | M21: =IF(ISBLANK(D21), "", IFERROR(PROPER(TEXT(D21,"mmmm")),"")) -> Abril | N21: =H21 -> 4789-0/01 - Comércio varejista de suvenires, bijuterias e artesanatos | O21: =IFERROR(RIGHT(N21,LEN(N21)-SEARCH("- ",N21)-1),"") -> Comércio varejista de suvenires, bijuterias e artesanatos | Q21: ='CNAE_Cód.Atividade Econômica'!B388 -> Atividades de sauna e banhos | R21: =COUNTIF($O:$O,Q21) -> 0 | S21: =Q21 -> Atividades de sauna e banhos | U21: =COUNTIF(R$10:R21,R21) -> 4 | V21: =R21&U21 -> 04 | W21: =INDEX($S$10:$S$401, MATCH(V21,$V$10:$V$1048576, 0)) -> Atividades de sauna e banhos | Y21: 12 | Z21: =LARGE($R$10:$R$1048576,Y21) -> 0 | AA21: =INDEX(S$10:S$1000, MATCH(R21, R$10:R$1000, 0)) -> Guarda-móveis | AB21: =COUNTIF(R$10:R21,R21) -> 4 | AC21: =R21&U21 -> 04 | AD21: =INDEX($S$10:$S$1048576, MATCH(AC21, $V$10:$V$1048576, 0)) -> Atividades de sauna e banhos | AE21: =Z21 -> 0
D22: 45383 | E22: EMPRESA M | F22: 00.111.222/0001-12 | G22: EPP (Empresa de Pequeno Porte) | H22: 4785-7/01 - Comércio varejista de antigüidades | I22: Carla | J22: Vendas | K22: Aprovado | M22: =IF(ISBLANK(D22), "", IFERROR(PROPER(TEXT(D22,"mmmm")),"")) -> Abril | N22: =H22 -> 4785-7/01 - Comércio varejista de antigüidades | O22: =IFERROR(RIGHT(N22,LEN(N22)-SEARCH("- ",N22)-1),"") -> Comércio varejista de antigüidades | Q22: ='CNAE_Cód.Atividade Econômica'!B7 -> Serviço de laboratório óptico | R22: =COUNTIF($O:$O,Q22) -> 0 | S22: =Q22 -> Serviço de laboratório óptico | U22: =COUNTIF(R$10:R22,R22) -> 5 | V22: =R22&U22 -> 05 | W22: =INDEX($S$10:$S$401, MATCH(V22,$V$10:$V$1048576, 0)) -> Serviço de laboratório óptico | Y22: 13 | Z22: =LARGE($R$10:$R$1048576,Y22) -> 0 | AA22: =INDEX(S$10:S$1000, MATCH(R22, R$10:R$1000, 0)) -> Guarda-móveis | AB22: =COUNTIF(R$10:R22,R22) -> 5 | AC22: =R22&U22 -> 05 | AD22: =INDEX($S$10:$S$1048576, MATCH(AC22, $V$10:$V$1048576, 0)) -> Serviço de laboratório óptico | AE22: =Z22 -> 0
D23: 45413 | E23: EMPRESA N | F23: 00.111.222/0001-13 | G23: LTDA (Sociedade Limitada) | H23: 4785-7/01 - Comércio varejista de antigüidades | I23: Carla | J23: Vendas | K23: Em Análise | M23: =IF(ISBLANK(D23), "", IFERROR(PROPER(TEXT(D23,"mmmm")),"")) -> Maio | N23: =IF(H23="","",H23) -> 4785-7/01 - Comércio varejista de antigüidades | O23: =IFERROR(RIGHT(N23,LEN(N23)-SEARCH("- ",N23)-1),"") -> Comércio varejista de antigüidades | Q23: ='CNAE_Cód.Atividade Econômica'!B389 -> Serviços de tatuagem e colocação de piercing | R23: =COUNTIF($O:$O,Q23) -> 0 | S23: =Q23 -> Serviços de tatuagem e colocação de piercing | U23: =COUNTIF(R$10:R23,R23) -> 6 | V23: =R23&U23 -> 06 | W23: =INDEX($S$10:$S$401, MATCH(V23,$V$10:$V$1048576, 0)) -> Serviços de tatuagem e colocação de piercing | Y23: 14 | Z23: =LARGE($R$10:$R$1048576,Y23) -> 0 | AA23: =INDEX(S$10:S$1000, MATCH(R23, R$10:R$1000, 0)) -> Guarda-móveis | AB23: =COUNTIF(R$10:R23,R23) -> 6 | AC23: =R23&U23 -> 06 | AD23: =INDEX($S$10:$S$1048576, MATCH(AC23, $V$10:$V$1048576, 0)) -> Serviços de tatuagem e colocação de piercing | AE23: =Z23 -> 0
D24: 45413 | E24: EMPRESA O | F24: 00.111.222/0001-14 | G24: LTDA (Sociedade Limitada) | H24: 4785-7/01 - Comércio varejista de antigüidades | I24: Carla | J24: Vendas | K24: Em Análise | M24: =IF(ISBLANK(D24), "", IFERROR(PROPER(TEXT(D24,"mmmm")),"")) -> Maio | N24: =IF(H24="","",H24) -> 4785-7/01 - Comércio varejista de antigüidades | O24: =IFERROR(RIGHT(N24,LEN(N24)-SEARCH("- ",N24)-1),"") -> Comércio varejista de antigüidades | Q24: ='CNAE_Cód.Atividade Econômica'!B158 -> Comércio varejista de armas e munições | R24: =COUNTIF($O:$O,Q24) -> 0 | S24: =Q24 -> Comércio varejista de armas e munições | U24: =COUNTIF(R$10:R24,R24) -> 7 | V24: =R24&U24 -> 07 | W24: =INDEX($S$10:$S$401, MATCH(V24,$V$10:$V$1048576, 0)) -> Comércio varejista de armas e munições | Y24: 15 | Z24: =LARGE($R$10:$R$1048576,Y24) -> 0 | AA24: =INDEX(S$10:S$1000, MATCH(R24, R$10:R$1000, 0)) -> Guarda-móveis | AB24: =COUNTIF(R$10:R24,R24) -> 7 | AC24: =R24&U24 -> 07 | AD24: =INDEX($S$10:$S$1048576, MATCH(AC24, $V$10:$V$1048576, 0)) -> Comércio varejista de armas e munições | AE24: =Z24 -> 0
D25: 45413 | E25: EMPRESA P | F25: 00.111.222/0001-15 | G25: LTDA (Sociedade Limitada) | H25: 4785-7/01 - Comércio varejista de antigüidades | I25: Carla | J25: Vendas | K25: Em Análise | M25: =IF(ISBLANK(D25), "", IFERROR(PROPER(TEXT(D25,"mmmm")),"")) -> Maio | N25: =IF(H25="","",H25) -> 4785-7/01 - Comércio varejista de antigüidades | O25: =IFERROR(RIGHT(N25,LEN(N25)-SEARCH("- ",N25)-1),"") -> Comércio varejista de antigüidades | Q25: ='CNAE_Cód.Atividade Econômica'!B3 -> Serviço de manejo de animais | R25: =COUNTIF($O:$O,Q25) -> 0 | S25: =Q25 -> Serviço de manejo de animais | U25: =COUNTIF(R$10:R25,R25) -> 8 | V25: =R25&U25 -> 08 | W25: =INDEX($S$10:$S$401, MATCH(V25,$V$10:$V$1048576, 0)) -> Serviço de manejo de animais | Y25: 16 | Z25: =LARGE($R$10:$R$1048576,Y25) -> 0 | AA25: =INDEX(S$10:S$1000, MATCH(R25, R$10:R$1000, 0)) -> Guarda-móveis | AB25: =COUNTIF(R$10:R25,R25) -> 8 | AC25: =R25&U25 -> 08 | AD25: =INDEX($S$10:$S$1048576, MATCH(AC25, $V$10:$V$1048576, 0)) -> Serviço de manejo de animais | AE25: =Z25 -> 0
D26: 45414 | E26: EMPRESA Q | F26: 00.111.222/0001-16 | G26: LTDA (Sociedade Limitada) | H26: 4785-7/01 - Comércio varejista de antigüidades | I26: Carla | J26: Vendas | K26: Em Análise | M26: =IF(ISBLANK(D26), "", IFERROR(PROPER(TEXT(D26,"mmmm")),"")) -> Maio | N26: =IF(H26="","",H26) -> 4785-7/01 - Comércio varejista de antigüidades | O26: =IFERROR(RIGHT(N26,LEN(N26)-SEARCH("- ",N26)-1),"") -> Comércio varejista de antigüidades | Q26: ='CNAE_Cód.Atividade Econômica'!B4 -> Atividades de apoio à aqüicultura em água doce | R26: =COUNTIF($O:$O,Q26) -> 0 | S26: =Q26 -> Atividades de apoio à aqüicultura em água doce | U26: =COUNTIF(R$10:R26,R26) -> 9 | V26: =R26&U26 -> 09 | W26: =INDEX($S$10:$S$401, MATCH(V26,$V$10:$V$1048576, 0)) -> Atividades de apoio à aqüicultura em água doce | Y26: 17 | Z26: =LARGE($R$10:$R$1048576,Y26) -> 0 | AA26: =INDEX(S$10:S$1000, MATCH(R26, R$10:R$1000, 0)) -> Guarda-móveis | AB26: =COUNTIF(R$10:R26,R26) -> 9 | AC26: =R26&U26 -> 09 | AD26: =INDEX($S$10:$S$1048576, MATCH(AC26, $V$10:$V$1048576, 0)) -> Atividades de apoio à aqüicultura em água doce | AE26: =Z26 -> 0
D27: 45446 | E27: EMPRESA R | F27: 00.111.222/0001-17 | G27: EPP (Empresa de Pequeno Porte) | H27: 4785-7/01 - Comércio varejista de antigüidades | I27: Carla | J27: Vendas | K27: Aprovado | M27: =IF(ISBLANK(D27), "", IFERROR(PROPER(TEXT(D27,"mmmm")),"")) -> Junho | N27: =IF(H27="","",H27) -> 4785-7/01 - Comércio varejista de antigüidades | O27: =IFERROR(RIGHT(N27,LEN(N27)-SEARCH("- ",N27)-1),"") -> Comércio varejista de antigüidades | Q27: ='CNAE_Cód.Atividade Econômica'!B5 -> Fabricação de gelo comum | R27: =COUNTIF($O:$O,Q27) -> 0 | S27: =Q27 -> Fabricação de gelo comum | U27: =COUNTIF(R$10:R27,R27) -> 10 | V27: =R27&U27 -> 010 | W27: =INDEX($S$10:$S$401, MATCH(V27,$V$10:$V$1048576, 0)) -> Fabricação de gelo comum | Y27: 18 | Z27: =LARGE($R$10:$R$1048576,Y27) -> 0 | AA27: =INDEX(S$10:S$1000, MATCH(R27, R$10:R$1000, 0)) -> Guarda-móveis | AB27: =COUNTIF(R$10:R27,R27) -> 10 | AC27: =R27&U27 -> 010 | AD27: =INDEX($S$10:$S$1048576, MATCH(AC27, $V$10:$V$1048576, 0)) -> Fabricação de gelo comum | AE27: =Z27 -> 0
D28: 45446 | E28: EMPRESA S | F28: 00.111.222/0001-18 | G28: EPP (Empresa de Pequeno Porte) | H28: 4785-7/01 - Comércio varejista de antigüidades | I28: Carla | J28: Vendas | K28: Aprovado | M28: =IF(ISBLANK(D28), "", IFERROR(PROPER(TEXT(D28,"mmmm")),"")) -> Junho | N28: =IF(H28="","",H28) -> 4785-7/01 - Comércio varejista de antigüidades | O28: =IFERROR(RIGHT(N28,LEN(N28)-SEARCH("- ",N28)-1),"") -> Comércio varejista de antigüidades | Q28: ='CNAE_Cód.Atividade Econômica'!B6 -> Serviços de prótese dentária | R28: =COUNTIF($O:$O,Q28) -> 0 | S28: =Q28 -> Serviços de prótese dentária | U28: =COUNTIF(R$10:R28,R28) -> 11 | V28: =R28&U28 -> 011 | W28: =INDEX($S$10:$S$401, MATCH(V28,$V$10:$V$1048576, 0)) -> Serviços de prótese dentária | Y28: 19 | Z28: =LARGE($R$10:$R$1048576,Y28) -> 0 | AA28: =INDEX(S$10:S$1000, MATCH(R28, R$10:R$1000, 0)) -> Guarda-móveis | AB28: =COUNTIF(R$10:R28,R28) -> 11 | AC28: =R28&U28 -> 011 | AD28: =INDEX($S$10:$S$1048576, MATCH(AC28, $V$10:$V$1048576, 0)) -> Serviços de prótese dentária | AE28: =Z28 -> 0
D29: 45478 | E29: EMPRESA T | F29: 00.111.222/0001-19 | G29: EPP (Empresa de Pequeno Porte) | H29: 4783-1/02 - Comércio varejista de artigos de relojoaria | I29: Carla | J29: Vendas | K29: Aprovado | M29: =IF(ISBLANK(D29), "", IFERROR(PROPER(TEXT(D29,"mmmm")),"")) -> Julho | N29: =IF(H29="","",H29) -> 4783-1/02 - Comércio varejista de artigos de relojoaria | O29: =IFERROR(RIGHT(N29,LEN(N29)-SEARCH("- ",N29)-1),"") -> Comércio varejista de artigos de relojoaria | Q29: ='CNAE_Cód.Atividade Econômica'!B8 -> Manutenção e reparação de aparelhos e instrumentos de medida, teste e controle | R29: =COUNTIF($O:$O,Q29) -> 0 | S29: =Q29 -> Manutenção e reparação de aparelhos e instrumentos de medida, teste e controle | U29: =COUNTIF(R$10:R29,R29) -> 12 | V29: =R29&U29 -> 012 | W29: =INDEX($S$10:$S$401, MATCH(V29,$V$10:$V$1048576, 0)) -> Manutenção e reparação de aparelhos e instrumentos de medida, teste e controle | Y29: 20 | Z29: =LARGE($R$10:$R$1048576,Y29) -> 0 | AA29: =INDEX(S$10:S$1000, MATCH(R29, R$10:R$1000, 0)) -> Guarda-móveis | AB29: =COUNTIF(R$10:R29,R29) -> 12 | AC29: =R29&U29 -> 012 | AD29: =INDEX($S$10:$S$1048576, MATCH(AC29, $V$10:$V$1048576, 0)) -> Manutenção e reparação de aparelhos e instrumentos de medida, teste e controle | AE29: =Z29 -> 0
D30: 45478 | E30: EMPRESA U | F30: 00.111.222/0001-20 | G30: EPP (Empresa de Pequeno Porte) | H30: 4783-1/02 - Comércio varejista de artigos de relojoaria | I30: Carla | J30: Vendas | K30: Aprovado | M30: =IF(ISBLANK(D30), "", IFERROR(PROPER(TEXT(D30,"mmmm")),"")) -> Julho | N30: =IF(H30="","",H30) -> 4783-1/02 - Comércio varejista de artigos de relojoaria | O30: =IFERROR(RIGHT(N30,LEN(N30)-SEARCH("- ",N30)-1),"") -> Comércio varejista de artigos de relojoaria | Q30: ='CNAE_Cód.Atividade Econômica'!B9 -> Manutenção e reparação de aparelhos eletromédicos e eletroterapêuticos e equipamentos de irradiação | R30: =COUNTIF($O:$O,Q30) -> 0 | S30: =Q30 -> Manutenção e reparação de aparelhos eletromédicos e eletroterapêuticos e equipamentos de irradiação | U30: =COUNTIF(R$10:R30,R30) -> 13 | V30: =R30&U30 -> 013 | W30: =INDEX($S$10:$S$401, MATCH(V30,$V$10:$V$1048576, 0)) -> Manutenção e reparação de aparelhos eletromédicos e eletroterapêuticos e equipamentos de irradiação | Y30: 21 | Z30: =LARGE($R$10:$R$1048576,Y30) -> 0 | AA30: =INDEX(S$10:S$1000, MATCH(R30, R$10:R$1000, 0)) -> Guarda-móveis | AB30: =COUNTIF(R$10:R30,R30) -> 13 | AC30: =R30&U30 -> 013 | AD30: =INDEX($S$10:$S$1048576, MATCH(AC30, $V$10:$V$1048576, 0)) -> Manutenção e reparação de aparelhos eletromédicos e eletroterapêuticos e equipamentos de irradiação | AE30: =Z30 -> 0
D31: 45511 | E31: EMPRESA V | F31: 00.111.222/0001-21 | G31: S/A (Sociedade Anônima)Sociedade Anônima | H31: 4789-0/03 - Comércio varejista de objetos de arte | I31: Carla | J31: Vendas | K31: Aprovado | M31: =IF(ISBLANK(D31), "", IFERROR(PROPER(TEXT(D31,"mmmm")),"")) -> Agosto | N31: =IF(H31="","",H31) -> 4789-0/03 - Comércio varejista de objetos de arte | O31: =IFERROR(RIGHT(N31,LEN(N31)-SEARCH("- ",N31)-1),"") -> Comércio varejista de objetos de arte | Q31: ='CNAE_Cód.Atividade Econômica'!B10 -> Manutenção e reparação de equipamentos e instrumentos ópticos | R31: =COUNTIF($O:$O,Q31) -> 0 | S31: =Q31 -> Manutenção e reparação de equipamentos e instrumentos ópticos | U31: =COUNTIF(R$10:R31,R31) -> 14 | V31: =R31&U31 -> 014 | W31: =INDEX($S$10:$S$401, MATCH(V31,$V$10:$V$1048576, 0)) -> Manutenção e reparação de equipamentos e instrumentos ópticos | Y31: 22 | Z31: =LARGE($R$10:$R$1048576,Y31) -> 0 | AA31: =INDEX(S$10:S$1000, MATCH(R31, R$10:R$1000, 0)) -> Guarda-móveis | AB31: =COUNTIF(R$10:R31,R31) -> 14 | AC31: =R31&U31 -> 014 | AD31: =INDEX($S$10:$S$1048576, MATCH(AC31, $V$10:$V$1048576, 0)) -> Manutenção e reparação de equipamentos e instrumentos ópticos | AE31: =Z31 -> 0
D32: 45511 | E32: EMPRESA W | F32: 00.111.222/0001-22 | G32: S/A (Sociedade Anônima)Sociedade Anônima | H32: 4789-0/02 - Comércio varejista de plantas e flores naturais | I32: Carla | J32: Vendas | K32: Aprovado | M32: =IF(ISBLANK(D32), "", IFERROR(PROPER(TEXT(D32,"mmmm")),"")) -> Agosto | N32: =IF(H32="","",H32) -> 4789-0/02 - Comércio varejista de plantas e flores naturais | O32: =IFERROR(RIGHT(N32,LEN(N32)-SEARCH("- ",N32)-1),"") -> Comércio varejista de plantas e flores naturais | Q32: ='CNAE_Cód.Atividade Econômica'!B11 -> Manutenção e reparação de geradores, transformadores e motores elétricos | R32: =COUNTIF($O:$O,Q32) -> 0 | S32: =Q32 -> Manutenção e reparação de geradores, transformadores e motores elétricos | U32: =COUNTIF(R$10:R32,R32) -> 15 | V32: =R32&U32 -> 015 | W32: =INDEX($S$10:$S$401, MATCH(V32,$V$10:$V$1048576, 0)) -> Manutenção e reparação de geradores, transformadores e motores elétricos | Y32: 23 | Z32: =LARGE($R$10:$R$1048576,Y32) -> 0 | AA32: =INDEX(S$10:S$1000, MATCH(R32, R$10:R$1000, 0)) -> Guarda-móveis | AB32: =COUNTIF(R$10:R32,R32) -> 15 | AC32: =R32&U32 -> 015 | AD32: =INDEX($S$10:$S$1048576, MATCH(AC32, $V$10:$V$1048576, 0)) -> Manutenção e reparação de geradores, transformadores e motores elétricos | AE32: =Z32 -> 0
D33: 45544 | E33: EMPRESA X | F33: 00.111.222/0001-23 | G33: S/A (Sociedade Anônima)Sociedade Anônima | H33: 5590-6/02 - Campings | I33: Carla | J33: Vendas | K33: Aprovado | M33: =IF(ISBLANK(D33), "", IFERROR(PROPER(TEXT(D33,"mmmm")),"")) -> Setembro | N33: =IF(H33="","",H33) -> 5590-6/02 - Campings | O33: =IFERROR(RIGHT(N33,LEN(N33)-SEARCH("- ",N33)-1),"") -> Campings | Q33: ='CNAE_Cód.Atividade Econômica'!B12 -> Manutenção e reparação de baterias e acumuladores elétricos, exceto para veículos | R33: =COUNTIF($O:$O,Q33) -> 0 | S33: =Q33 -> Manutenção e reparação de baterias e acumuladores elétricos, exceto para veículos | U33: =COUNTIF(R$10:R33,R33) -> 16 | V33: =R33&U33 -> 016 | W33: =INDEX($S$10:$S$401, MATCH(V33,$V$10:$V$1048576, 0)) -> Manutenção e reparação de baterias e acumuladores elétricos, exceto para veículos | Y33: 24 | Z33: =LARGE($R$10:$R$1048576,Y33) -> 0 | AA33: =INDEX(S$10:S$1000, MATCH(R33, R$10:R$1000, 0)) -> Guarda-móveis | AB33: =COUNTIF(R$10:R33,R33) -> 16 | AC33: =R33&U33 -> 016 | AD33: =INDEX($S$10:$S$1048576, MATCH(AC33, $V$10:$V$1048576, 0)) -> Manutenção e reparação de baterias e acumuladores elétricos, exceto para veículos | AE33: =Z33 -> 0
D34: 45544 | E34: EMPRESA Y | F34: 00.111.222/0001-24 | G34: S/A (Sociedade Anônima)Sociedade Anônima | H34: 4520-0/08 - Serviços de capotaria | I34: Carla | J34: Vendas | K34: Aprovado | M34: =IF(ISBLANK(D34), "", IFERROR(PROPER(TEXT(D34,"mmmm")),"")) -> Setembro | N34: =IF(H34="","",H34) -> 4520-0/08 - Serviços de capotaria | O34: =IFERROR(RIGHT(N34,LEN(N34)-SEARCH("- ",N34)-1),"") -> Serviços de capotaria | Q34: ='CNAE_Cód.Atividade Econômica'!B13 -> Manutenção e reparação de máquinas, aparelhos e materiais elétricos não especificados anteriormente | R34: =COUNTIF($O:$O,Q34) -> 0 | S34: =Q34 -> Manutenção e reparação de máquinas, aparelhos e materiais elétricos não especificados anteriormente | U34: =COUNTIF(R$10:R34,R34) -> 17 | V34: =R34&U34 -> 017 | W34: =INDEX($S$10:$S$401, MATCH(V34,$V$10:$V$1048576, 0)) -> Manutenção e reparação de máquinas, aparelhos e materiais elétricos não especificados anteriormente | Y34: 25 | Z34: =LARGE($R$10:$R$1048576,Y34) -> 0 | AA34: =INDEX(S$10:S$1000, MATCH(R34, R$10:R$1000, 0)) -> Guarda-móveis | AB34: =COUNTIF(R$10:R34,R34) -> 17 | AC34: =R34&U34 -> 017 | AD34: =INDEX($S$10:$S$1048576, MATCH(AC34, $V$10:$V$1048576, 0)) -> Manutenção e reparação de máquinas, aparelhos e materiais elétricos não especificados anteriormente | AE34: =Z34 -> 0
D35: 45545 | E35: EMPRESA Z | F35: 00.111.222/0001-25 | G35: LTDA (Sociedade Limitada) | H35: 4520-0/08 - Serviços de capotaria | I35: Carla | J35: Vendas | K35: Aprovado | M35: =IF(ISBLANK(D35), "", IFERROR(PROPER(TEXT(D35,"mmmm")),"")) -> Setembro | N35: =IF(H35="","",H35) -> 4520-0/08 - Serviços de capotaria | O35: =IFERROR(RIGHT(N35,LEN(N35)-SEARCH("- ",N35)-1),"") -> Serviços de capotaria | Q35: ='CNAE_Cód.Atividade Econômica'!B14 -> Manutenção e reparação de máquinas motrizes não-elétricas | R35: =COUNTIF($O:$O,Q35) -> 0 | S35: =Q35 -> Manutenção e reparação de máquinas motrizes não-elétricas | U35: =COUNTIF(R$10:R35,R35) -> 18 | V35: =R35&U35 -> 018 | W35: =INDEX($S$10:$S$401, MATCH(V35,$V$10:$V$1048576, 0)) -> Manutenção e reparação de máquinas motrizes não-elétricas | Y35: 26 | Z35: =LARGE($R$10:$R$1048576,Y35) -> 0 | AA35: =INDEX(S$10:S$1000, MATCH(R35, R$10:R$1000, 0)) -> Guarda-móveis | AB35: =COUNTIF(R$10:R35,R35) -> 18 | AC35: =R35&U35 -> 018 | AD35: =INDEX($S$10:$S$1048576, MATCH(AC35, $V$10:$V$1048576, 0)) -> Manutenção e reparação de máquinas motrizes não-elétricas | AE35: =Z35 -> 0
M36: =IF(ISBLANK(D36), "", IFERROR(PROPER(TEXT(D36,"mmmm")),"")) | N36: =IF(H36="","",H36) | O36: =IFERROR(RIGHT(N36,LEN(N36)-SEARCH("- ",N36)-1),"") | Q36: ='CNAE_Cód.Atividade Econômica'!B15 -> Manutenção e reparação de equipamentos hidráulicos e pneumáticos, exceto válvulas | R36: =COUNTIF($O:$O,Q36) -> 0 | S36: =Q36 -> Manutenção e reparação de equipamentos hidráulicos e pneumáticos, exceto válvulas | U36: =COUNTIF(R$10:R36,R36) -> 19 | V36: =R36&U36 -> 019 | W36: =INDEX($S$10:$S$401, MATCH(V36,$V$10:$V$1048576, 0)) -> Manutenção e reparação de equipamentos hidráulicos e pneumáticos, exceto válvulas | Y36: 27 | Z36: =LARGE($R$10:$R$1048576,Y36) -> 0 | AA36: =INDEX(S$10:S$1000, MATCH(R36, R$10:R$1000, 0)) -> Guarda-móveis | AB36: =COUNTIF(R$10:R36,R36) -> 19 | AC36: =R36&U36 -> 019 | AD36: =INDEX($S$10:$S$1048576, MATCH(AC36, $V$10:$V$1048576, 0)) -> Manutenção e reparação de equipamentos hidráulicos e pneumáticos, exceto válvulas | AE36: =Z36 -> 0
M37: =IF(ISBLANK(D37), "", IFERROR(PROPER(TEXT(D37,"mmmm")),"")) | N37: =IF(H37="","",H37) | O37: =IFERROR(RIGHT(N37,LEN(N37)-SEARCH("- ",N37)-1),"") | Q37: ='CNAE_Cód.Atividade Econômica'!B16 -> Manutenção e reparação de válvulas industriais | R37: =COUNTIF($O:$O,Q37) -> 0 | S37: =Q37 -> Manutenção e reparação de válvulas industriais | U37: =COUNTIF(R$10:R37,R37) -> 20 | V37: =R37&U37 -> 020 | W37: =INDEX($S$10:$S$401, MATCH(V37,$V$10:$V$1048576, 0)) -> Manutenção e reparação de válvulas industriais | Y37: 28 | Z37: =LARGE($R$10:$R$1048576,Y37) -> 0 | AA37: =INDEX(S$10:S$1000, MATCH(R37, R$10:R$1000, 0)) -> Guarda-móveis | AB37: =COUNTIF(R$10:R37,R37) -> 20 | AC37: =R37&U37 -> 020 | AD37: =INDEX($S$10:$S$1048576, MATCH(AC37, $V$10:$V$1048576, 0)) -> Manutenção e reparação de válvulas industriais | AE37: =Z37 -> 0
M38: =IF(ISBLANK(D38), "", IFERROR(PROPER(TEXT(D38,"mmmm")),"")) | N38: =IF(H38="","",H38) | O38: =IFERROR(RIGHT(N38,LEN(N38)-SEARCH("- ",N38)-1),"") | Q38: ='CNAE_Cód.Atividade Econômica'!B17 -> Manutenção e reparação de compressores | R38: =COUNTIF($O:$O,Q38) -> 0 | S38: =Q38 -> Manutenção e reparação de compressores | U38: =COUNTIF(R$10:R38,R38) -> 21 | V38: =R38&U38 -> 021 | W38: =INDEX($S$10:$S$401, MATCH(V38,$V$10:$V$1048576, 0)) -> Manutenção e reparação de compressores | Y38: 29 | Z38: =LARGE($R$10:$R$1048576,Y38) -> 0 | AA38: =INDEX(S$10:S$1000, MATCH(R38, R$10:R$1000, 0)) -> Guarda-móveis | AB38: =COUNTIF(R$10:R38,R38) -> 21 | AC38: =R38&U38 -> 021 | AD38: =INDEX($S$10:$S$1048576, MATCH(AC38, $V$10:$V$1048576, 0)) -> Manutenção e reparação de compressores | AE38: =Z38 -> 0
M39: =IF(ISBLANK(D39), "", IFERROR(PROPER(TEXT(D39,"mmmm")),"")) | N39: =IF(H39="","",H39) | O39: =IFERROR(RIGHT(N39,LEN(N39)-SEARCH("- ",N39)-1),"") | Q39: ='CNAE_Cód.Atividade Econômica'!B18 -> Manutenção e reparação de equipamentos de transmissão para fins industriais | R39: =COUNTIF($O:$O,Q39) -> 0 | S39: =Q39 -> Manutenção e reparação de equipamentos de transmissão para fins industriais | U39: =COUNTIF(R$10:R39,R39) -> 22 | V39: =R39&U39 -> 022 | W39: =INDEX($S$10:$S$401, MATCH(V39,$V$10:$V$1048576, 0)) -> Manutenção e reparação de equipamentos de transmissão para fins industriais | Y39: 30 | Z39: =LARGE($R$10:$R$1048576,Y39) -> 0 | AA39: =INDEX(S$10:S$1000, MATCH(R39, R$10:R$1000, 0)) -> Guarda-móveis | AB39: =COUNTIF(R$10:R39,R39) -> 22 | AC39: =R39&U39 -> 022 | AD39: =INDEX($S$10:$S$1048576, MATCH(AC39, $V$10:$V$1048576, 0)) -> Manutenção e reparação de equipamentos de transmissão para fins industriais | AE39: =Z39 -> 0
M40: =IF(ISBLANK(D40), "", IFERROR(PROPER(TEXT(D40,"mmmm")),"")) | N40: =IF(H40="","",H40) | O40: =IFERROR(RIGHT(N40,LEN(N40)-SEARCH("- ",N40)-1),"") | Q40: ='CNAE_Cód.Atividade Econômica'!B19 -> Manutenção e reparação de máquinas, aparelhos e equipamentos para instalações térmicas | R40: =COUNTIF($O:$O,Q40) -> 0 | S40: =Q40 -> Manutenção e reparação de máquinas, aparelhos e equipamentos para instalações térmicas | U40: =COUNTIF(R$10:R40,R40) -> 23 | V40: =R40&U40 -> 023 | W40: =INDEX($S$10:$S$401, MATCH(V40,$V$10:$V$1048576, 0)) -> Manutenção e reparação de máquinas, aparelhos e equipamentos para instalações térmicas | Y40: 31 | Z40: =LARGE($R$10:$R$1048576,Y40) -> 0 | AA40: =INDEX(S$10:S$1000, MATCH(R40, R$10:R$1000, 0)) -> Guarda-móveis | AB40: =COUNTIF(R$10:R40,R40) -> 23 | AC40: =R40&U40 -> 023 | AD40: =INDEX($S$10:$S$1048576, MATCH(AC40, $V$10:$V$1048576, 0)) -> Manutenção e reparação de máquinas, aparelhos e equipamentos para instalações térmicas | AE40: =Z40 -> 0
M41: =IF(ISBLANK(D41), "", IFERROR(PROPER(TEXT(D41,"mmmm")),"")) | N41: =IF(H41="","",H41) | O41: =IFERROR(RIGHT(N41,LEN(N41)-SEARCH("- ",N41)-1),"") | Q41: ='CNAE_Cód.Atividade Econômica'!B20 -> Manutenção e reparação de máquinas e aparelhos de refrigeração e ventilação para uso industrial e comercial | R41: =COUNTIF($O:$O,Q41) -> 0 | S41: =Q41 -> Manutenção e reparação de máquinas e aparelhos de refrigeração e ventilação para uso industrial e comercial | U41: =COUNTIF(R$10:R41,R41) -> 24 | V41: =R41&U41 -> 024 | W41: =INDEX($S$10:$S$401, MATCH(V41,$V$10:$V$1048576, 0)) -> Manutenção e reparação de máquinas e aparelhos de refrigeração e ventilação para uso industrial e comercial | Y41: 32 | Z41: =LARGE($R$10:$R$1048576,Y41) -> 0 | AA41: =INDEX(S$10:S$1000, MATCH(R41, R$10:R$1000, 0)) -> Guarda-móveis | AB41: =COUNTIF(R$10:R41,R41) -> 24 | AC41: =R41&U41 -> 024 | AD41: =INDEX($S$10:$S$1048576, MATCH(AC41, $V$10:$V$1048576, 0)) -> Manutenção e reparação de máquinas e aparelhos de refrigeração e ventilação para uso industrial e comercial | AE41: =Z41 -> 0
M42: =IF(ISBLANK(D42), "", IFERROR(PROPER(TEXT(D42,"mmmm")),"")) | N42: =IF(H42="","",H42) | O42: =IFERROR(RIGHT(N42,LEN(N42)-SEARCH("- ",N42)-1),"") | Q42: ='CNAE_Cód.Atividade Econômica'!B21 -> Manutenção e reparação de máquinas, equipamentos e aparelhos para transporte e elevação de cargas | R42: =COUNTIF($O:$O,Q42) -> 0 | S42: =Q42 -> Manutenção e reparação de máquinas, equipamentos e aparelhos para transporte e elevação de cargas | U42: =COUNTIF(R$10:R42,R42) -> 25 | V42: =R42&U42 -> 025 | W42: =INDEX($S$10:$S$401, MATCH(V42,$V$10:$V$1048576, 0)) -> Manutenção e reparação de máquinas, equipamentos e aparelhos para transporte e elevação de cargas | Y42: 33 | Z42: =LARGE($R$10:$R$1048576,Y42) -> 0 | AA42: =INDEX(S$10:S$1000, MATCH(R42, R$10:R$1000, 0)) -> Guarda-móveis | AB42: =COUNTIF(R$10:R42,R42) -> 25 | AC42: =R42&U42 -> 025 | AD42: =INDEX($S$10:$S$1048576, MATCH(AC42, $V$10:$V$1048576, 0)) -> Manutenção e reparação de máquinas, equipamentos e aparelhos para transporte e elevação de cargas | AE42: =Z42 -> 0
M43: =IF(ISBLANK(D43), "", IFERROR(PROPER(TEXT(D43,"mmmm")),"")) | N43: =IF(H43="","",H43) | O43: =IFERROR(RIGHT(N43,LEN(N43)-SEARCH("- ",N43)-1),"") | Q43: ='CNAE_Cód.Atividade Econômica'!B22 -> Manutenção e reparação de máquinas de escrever, calcular e de outros equipamentos não-eletrônicos para escritório | R43: =COUNTIF($O:$O,Q43) -> 0 | S43: =Q43 -> Manutenção e reparação de máquinas de escrever, calcular e de outros equipamentos não-eletrônicos para escritório | U43: =COUNTIF(R$10:R43,R43) -> 26 | V43: =R43&U43 -> 026 | W43: =INDEX($S$10:$S$401, MATCH(V43,$V$10:$V$1048576, 0)) -> Manutenção e reparação de máquinas de escrever, calcular e de outros equipamentos não-eletrônicos para escritório | Y43: 34 | Z43: =LARGE($R$10:$R$1048576,Y43) -> 0 | AA43: =INDEX(S$10:S$1000, MATCH(R43, R$10:R$1000, 0)) -> Guarda-móveis | AB43: =COUNTIF(R$10:R43,R43) -> 26 | AC43: =R43&U43 -> 026 | AD43: =INDEX($S$10:$S$1048576, MATCH(AC43, $V$10:$V$1048576, 0)) -> Manutenção e reparação de máquinas de escrever, calcular e de outros equipamentos não-eletrônicos para escritório | AE43: =Z43 -> 0
M44: =IF(ISBLANK(D44), "", IFERROR(PROPER(TEXT(D44,"mmmm")),"")) | N44: =IF(H44="","",H44) | O44: =IFERROR(RIGHT(N44,LEN(N44)-SEARCH("- ",N44)-1),"") | Q44: ='CNAE_Cód.Atividade Econômica'!B23 -> Manutenção e reparação de máquinas e equipamentos para uso geral não especificados anteriormente | R44: =COUNTIF($O:$O,Q44) -> 0 | S44: =Q44 -> Manutenção e reparação de máquinas e equipamentos para uso geral não especificados anteriormente | U44: =COUNTIF(R$10:R44,R44) -> 27 | V44: =R44&U44 -> 027 | W44: =INDEX($S$10:$S$401, MATCH(V44,$V$10:$V$1048576, 0)) -> Manutenção e reparação de máquinas e equipamentos para uso geral não especificados anteriormente | Y44: 35 | Z44: =LARGE($R$10:$R$1048576,Y44) -> 0 | AA44: =INDEX(S$10:S$1000, MATCH(R44, R$10:R$1000, 0)) -> Guarda-móveis | AB44: =COUNTIF(R$10:R44,R44) -> 27 | AC44: =R44&U44 -> 027 | AD44: =INDEX($S$10:$S$1048576, MATCH(AC44, $V$10:$V$1048576, 0)) -> Manutenção e reparação de máquinas e equipamentos para uso geral não especificados anteriormente | AE44: =Z44 -> 0
M45: =IF(ISBLANK(D45), "", IFERROR(PROPER(TEXT(D45,"mmmm")),"")) | N45: =IF(H45="","",H45) | O45: =IFERROR(RIGHT(N45,LEN(N45)-SEARCH("- ",N45)-1),"") | Q45: ='CNAE_Cód.Atividade Econômica'!B24 -> Manutenção e reparação de máquinas e equipamentos para agricultura e pecuária | R45: =COUNTIF($O:$O,Q45) -> 0 | S45: =Q45 -> Manutenção e reparação de máquinas e equipamentos para agricultura e pecuária | U45: =COUNTIF(R$10:R45,R45) -> 28 | V45: =R45&U45 -> 028 | W45: =INDEX($S$10:$S$401, MATCH(V45,$V$10:$V$1048576, 0)) -> Manutenção e reparação de máquinas e equipamentos para agricultura e pecuária | Y45: 36 | Z45: =LARGE($R$10:$R$1048576,Y45) -> 0 | AA45: =INDEX(S$10:S$1000, MATCH(R45, R$10:R$1000, 0)) -> Guarda-móveis | AB45: =COUNTIF(R$10:R45,R45) -> 28 | AC45: =R45&U45 -> 028 | AD45: =INDEX($S$10:$S$1048576, MATCH(AC45, $V$10:$V$1048576, 0)) -> Manutenção e reparação de máquinas e equipamentos para agricultura e pecuária | AE45: =Z45 -> 0
M46: =IF(ISBLANK(D46), "", IFERROR(PROPER(TEXT(D46,"mmmm")),"")) | N46: =IF(H46="","",H46) | O46: =IFERROR(RIGHT(N46,LEN(N46)-SEARCH("- ",N46)-1),"") | Q46: ='CNAE_Cód.Atividade Econômica'!B25 -> Manutenção e reparação de tratores agrícolas | R46: =COUNTIF($O:$O,Q46) -> 0 | S46: =Q46 -> Manutenção e reparação de tratores agrícolas | U46: =COUNTIF(R$10:R46,R46) -> 29 | V46: =R46&U46 -> 029 | W46: =INDEX($S$10:$S$401, MATCH(V46,$V$10:$V$1048576, 0)) -> Manutenção e reparação de tratores agrícolas | Y46: 37 | Z46: =LARGE($R$10:$R$1048576,Y46) -> 0 | AA46: =INDEX(S$10:S$1000, MATCH(R46, R$10:R$1000, 0)) -> Guarda-móveis | AB46: =COUNTIF(R$10:R46,R46) -> 29 | AC46: =R46&U46 -> 029 | AD46: =INDEX($S$10:$S$1048576, MATCH(AC46, $V$10:$V$1048576, 0)) -> Manutenção e reparação de tratores agrícolas | AE46: =Z46 -> 0
M47: =IF(ISBLANK(D47), "", IFERROR(PROPER(TEXT(D47,"mmmm")),"")) | N47: =IF(H47="","",H47) | O47: =IFERROR(RIGHT(N47,LEN(N47)-SEARCH("- ",N47)-1),"") | Q47: ='CNAE_Cód.Atividade Econômica'!B26 -> Manutenção e reparação de máquinas-ferramenta | R47: =COUNTIF($O:$O,Q47) -> 0 | S47: =Q47 -> Manutenção e reparação de máquinas-ferramenta | U47: =COUNTIF(R$10:R47,R47) -> 30 | V47: =R47&U47 -> 030 | W47: =INDEX($S$10:$S$401, MATCH(V47,$V$10:$V$1048576, 0)) -> Manutenção e reparação de máquinas-ferramenta | Y47: 38 | Z47: =LARGE($R$10:$R$1048576,Y47) -> 0 | AA47: =INDEX(S$10:S$1000, MATCH(R47, R$10:R$1000, 0)) -> Guarda-móveis | AB47: =COUNTIF(R$10:R47,R47) -> 30 | AC47: =R47&U47 -> 030 | AD47: =INDEX($S$10:$S$1048576, MATCH(AC47, $V$10:$V$1048576, 0)) -> Manutenção e reparação de máquinas-ferramenta | AE47: =Z47 -> 0
... M88: =IF(ISBLANK(D88), "", IFERROR(PROPER(TEXT(D88,"mmmm")),"")) | N88: =IF(H88="","",H88) | O88: =IFERROR(RIGHT(N88,LEN(N88)-SEARCH("- ",N88)-1),"") | Q88: ='CNAE_Cód.Atividade Econômica'!B67 -> Serviços de instalação, manutenção e reparação de acessórios para veículos automotores | R88: =COUNTIF($O:$O,Q88) -> 0 | S88: =Q88 -> Serviços de instalação, manutenção e reparação de acessórios para veículos automotores | U88: =COUNTIF(R$10:R88,R88) -> 71 | V88: =R88&U88 -> 071 | W88: =INDEX($S$10:$S$401, MATCH(V88,$V$10:$V$1048576, 0)) -> Serviços de instalação, manutenção e reparação de acessórios para veículos automotores | Y88: 79 | Z88: =LARGE($R$10:$R$1048576,Y88) -> 0 | AA88: =INDEX(S$10:S$1000, MATCH(R88, R$10:R$1000, 0)) -> Guarda-móveis | AB88: =COUNTIF(R$10:R88,R88) -> 71 | AC88: =R88&U88 -> 071 | AD88: =INDEX($S$10:$S$1048576, MATCH(AC88, $V$10:$V$1048576, 0)) -> Serviços de instalação, manutenção e reparação de acessórios para veículos automotores | AE88: =Z88 -> 0
M89: =IF(ISBLANK(D89), "", IFERROR(PROPER(TEXT(D89,"mmmm")),"")) | N89: =IF(H89="","",H89) | O89: =IFERROR(RIGHT(N89,LEN(N89)-SEARCH("- ",N89)-1),"") | Q89: ='CNAE_Cód.Atividade Econômica'!B69 -> Comércio por atacado de peças e acessórios novos para veículos automotores | R89: =COUNTIF($O:$O,Q89) -> 0 | S89: =Q89 -> Comércio por atacado de peças e acessórios novos para veículos automotores | U89: =COUNTIF(R$10:R89,R89) -> 72 | V89: =R89&U89 -> 072 | W89: =INDEX($S$10:$S$401, MATCH(V89,$V$10:$V$1048576, 0)) -> Comércio por atacado de peças e acessórios novos para veículos automotores | Y89: 80 | Z89: =LARGE($R$10:$R$1048576,Y89) -> 0 | AA89: =INDEX(S$10:S$1000, MATCH(R89, R$10:R$1000, 0)) -> Guarda-móveis | AB89: =COUNTIF(R$10:R89,R89) -> 72 | AC89: =R89&U89 -> 072 | AD89: =INDEX($S$10:$S$1048576, MATCH(AC89, $V$10:$V$1048576, 0)) -> Comércio por atacado de peças e acessórios novos para veículos automotores | AE89: =Z89 -> 0
M90: =IF(ISBLANK(D90), "", IFERROR(PROPER(TEXT(D90,"mmmm")),"")) | N90: =IF(H90="","",H90) | O90: =IFERROR(RIGHT(N90,LEN(N90)-SEARCH("- ",N90)-1),"") | Q90: ='CNAE_Cód.Atividade Econômica'!B70 -> Comércio por atacado de pneumáticos e câmaras-de-ar | R90: =COUNTIF($O:$O,Q90) -> 0 | S90: =Q90 -> Comércio por atacado de pneumáticos e câmaras-de-ar | U90: =COUNTIF(R$10:R90,R90) -> 73 | V90: =R90&U90 -> 073 | W90: =INDEX($S$10:$S$401, MATCH(V90,$V$10:$V$1048576, 0)) -> Comércio por atacado de pneumáticos e câmaras-de-ar | Y90: 81 | Z90: =LARGE($R$10:$R$1048576,Y90) -> 0 | AA90: =INDEX(S$10:S$1000, MATCH(R90, R$10:R$1000, 0)) -> Guarda-móveis | AB90: =COUNTIF(R$10:R90,R90) -> 73 | AC90: =R90&U90 -> 073 | AD90: =INDEX($S$10:$S$1048576, MATCH(AC90, $V$10:$V$1048576, 0)) -> Comércio por atacado de pneumáticos e câmaras-de-ar | AE90: =Z90 -> 0
M91: =IF(ISBLANK(D91), "", IFERROR(PROPER(TEXT(D91,"mmmm")),"")) | N91: =IF(H91="","",H91) | O91: =IFERROR(RIGHT(N91,LEN(N91)-SEARCH("- ",N91)-1),"") | Q91: ='CNAE_Cód.Atividade Econômica'!B71 -> Comércio a varejo de peças e acessórios novos para veículos automotores | R91: =COUNTIF($O:$O,Q91) -> 0 | S91: =Q91 -> Comércio a varejo de peças e acessórios novos para veículos automotores | U91: =COUNTIF(R$10:R91,R91) -> 74 | V91: =R91&U91 -> 074 | W91: =INDEX($S$10:$S$401, MATCH(V91,$V$10:$V$1048576, 0)) -> Comércio a varejo de peças e acessórios novos para veículos automotores | Y91: 82 | Z91: =LARGE($R$10:$R$1048576,Y91) -> 0 | AA91: =INDEX(S$10:S$1000, MATCH(R91, R$10:R$1000, 0)) -> Guarda-móveis | AB91: =COUNTIF(R$10:R91,R91) -> 74 | AC91: =R91&U91 -> 074 | AD91: =INDEX($S$10:$S$1048576, MATCH(AC91, $V$10:$V$1048576, 0)) -> Comércio a varejo de peças e acessórios novos para veículos automotores | AE91: =Z91 -> 0
M92: =IF(ISBLANK(D92), "", IFERROR(PROPER(TEXT(D92,"mmmm")),"")) | N92: =IF(H92="","",H92) | O92: =IFERROR(RIGHT(N92,LEN(N92)-SEARCH("- ",N92)-1),"") | Q92: ='CNAE_Cód.Atividade Econômica'!B72 -> Comércio a varejo de peças e acessórios usados para veículos automotores | R92: =COUNTIF($O:$O,Q92) -> 0 | S92: =Q92 -> Comércio a varejo de peças e acessórios usados para veículos automotores | U92: =COUNTIF(R$10:R92,R92) -> 75 | V92: =R92&U92 -> 075 | W92: =INDEX($S$10:$S$401, MATCH(V92,$V$10:$V$1048576, 0)) -> Comércio a varejo de peças e acessórios usados para veículos automotores | Y92: 83 | Z92: =LARGE($R$10:$R$1048576,Y92) -> 0 | AA92: =INDEX(S$10:S$1000, MATCH(R92, R$10:R$1000, 0)) -> Guarda-móveis | AB92: =COUNTIF(R$10:R92,R92) -> 75 | AC92: =R92&U92 -> 075 | AD92: =INDEX($S$10:$S$1048576, MATCH(AC92, $V$10:$V$1048576, 0)) -> Comércio a varejo de peças e acessórios usados para veículos automotores | AE92: =Z92 -> 0
M93: =IF(ISBLANK(D93), "", IFERROR(PROPER(TEXT(D93,"mmmm")),"")) | N93: =IF(H93="","",H93) | O93: =IFERROR(RIGHT(N93,LEN(N93)-SEARCH("- ",N93)-1),"") | Q93: ='CNAE_Cód.Atividade Econômica'!B73 -> Comércio a varejo de pneumáticos e câmaras-de-ar | R93: =COUNTIF($O:$O,Q93) -> 0 | S93: =Q93 -> Comércio a varejo de pneumáticos e câmaras-de-ar | U93: =COUNTIF(R$10:R93,R93) -> 76 | V93: =R93&U93 -> 076 | W93: =INDEX($S$10:$S$401, MATCH(V93,$V$10:$V$1048576, 0)) -> Comércio a varejo de pneumáticos e câmaras-de-ar | Y93: 84 | Z93: =LARGE($R$10:$R$1048576,Y93) -> 0 | AA93: =INDEX(S$10:S$1000, MATCH(R93, R$10:R$1000, 0)) -> Guarda-móveis | AB93: =COUNTIF(R$10:R93,R93) -> 76 | AC93: =R93&U93 -> 076 | AD93: =INDEX($S$10:$S$1048576, MATCH(AC93, $V$10:$V$1048576, 0)) -> Comércio a varejo de pneumáticos e câmaras-de-ar | AE93: =Z93 -> 0
M94: =IF(ISBLANK(D94), "", IFERROR(PROPER(TEXT(D94,"mmmm")),"")) | N94: =IF(H94="","",H94) | O94: =IFERROR(RIGHT(N94,LEN(N94)-SEARCH("- ",N94)-1),"") | Q94: ='CNAE_Cód.Atividade Econômica'!B74 -> Representantes comerciais e agentes do comércio de peças e acessórios novos e usados para veículos automotores | R94: =COUNTIF($O:$O,Q94) -> 0 | S94: =Q94 -> Representantes comerciais e agentes do comércio de peças e acessórios novos e usados para veículos automotores | U94: =COUNTIF(R$10:R94,R94) -> 77 | V94: =R94&U94 -> 077 | W94: =INDEX($S$10:$S$401, MATCH(V94,$V$10:$V$1048576, 0)) -> Representantes comerciais e agentes do comércio de peças e acessórios novos e usados para veículos automotores | Y94: 85 | Z94: =LARGE($R$10:$R$1048576,Y94) -> 0 | AA94: =INDEX(S$10:S$1000, MATCH(R94, R$10:R$1000, 0)) -> Guarda-móveis | AB94: =COUNTIF(R$10:R94,R94) -> 77 | AC94: =R94&U94 -> 077 | AD94: =INDEX($S$10:$S$1048576, MATCH(AC94, $V$10:$V$1048576, 0)) -> Representantes comerciais e agentes do comércio de peças e acessórios novos e usados para veículos automotores | AE94: =Z94 -> 0
M95: =IF(ISBLANK(D95), "", IFERROR(PROPER(TEXT(D95,"mmmm")),"")) | N95: =IF(H95="","",H95) | O95: =IFERROR(RIGHT(N95,LEN(N95)-SEARCH("- ",N95)-1),"") | Q95: ='CNAE_Cód.Atividade Econômica'!B75 -> Comércio por atacado de peças e acessórios para motocicletas e motonetas | R95: =COUNTIF($O:$O,Q95) -> 0 | S95: =Q95 -> Comércio por atacado de peças e acessórios para motocicletas e motonetas | U95: =COUNTIF(R$10:R95,R95) -> 78 | V95: =R95&U95 -> 078 | W95: =INDEX($S$10:$S$401, MATCH(V95,$V$10:$V$1048576, 0)) -> Comércio por atacado de peças e acessórios para motocicletas e motonetas | Y95: 86 | Z95: =LARGE($R$10:$R$1048576,Y95) -> 0 | AA95: =INDEX(S$10:S$1000, MATCH(R95, R$10:R$1000, 0)) -> Guarda-móveis | AB95: =COUNTIF(R$10:R95,R95) -> 78 | AC95: =R95&U95 -> 078 | AD95: =INDEX($S$10:$S$1048576, MATCH(AC95, $V$10:$V$1048576, 0)) -> Comércio por atacado de peças e acessórios para motocicletas e motonetas | AE95: =Z95 -> 0
M96: =IF(ISBLANK(D96), "", IFERROR(PROPER(TEXT(D96,"mmmm")),"")) | N96: =IF(H96="","",H96) | O96: =IFERROR(RIGHT(N96,LEN(N96)-SEARCH("- ",N96)-1),"") | Q96: ='CNAE_Cód.Atividade Econômica'!B76 -> Comércio a varejo de motocicletas e motonetas novas | R96: =COUNTIF($O:$O,Q96) -> 0 | S96: =Q96 -> Comércio a varejo de motocicletas e motonetas novas | U96: =COUNTIF(R$10:R96,R96) -> 79 | V96: =R96&U96 -> 079 | W96: =INDEX($S$10:$S$401, MATCH(V96,$V$10:$V$1048576, 0)) -> Comércio a varejo de motocicletas e motonetas novas | Y96: 87 | Z96: =LARGE($R$10:$R$1048576,Y96) -> 0 | AA96: =INDEX(S$10:S$1000, MATCH(R96, R$10:R$1000, 0)) -> Guarda-móveis | AB96: =COUNTIF(R$10:R96,R96) -> 79 | AC96: =R96&U96 -> 079 | AD96: =INDEX($S$10:$S$1048576, MATCH(AC96, $V$10:$V$1048576, 0)) -> Comércio a varejo de motocicletas e motonetas novas | AE96: =Z96 -> 0
M97: =IF(ISBLANK(D97), "", IFERROR(PROPER(TEXT(D97,"mmmm")),"")) | N97: =IF(H97="","",H97) | O97: =IFERROR(RIGHT(N97,LEN(N97)-SEARCH("- ",N97)-1),"") | Q97: ='CNAE_Cód.Atividade Econômica'!B77 -> Comércio a varejo de motocicletas e motonetas usadas | R97: =COUNTIF($O:$O,Q97) -> 0 | S97: =Q97 -> Comércio a varejo de motocicletas e motonetas usadas | U97: =COUNTIF(R$10:R97,R97) -> 80 | V97: =R97&U97 -> 080 | W97: =INDEX($S$10:$S$401, MATCH(V97,$V$10:$V$1048576, 0)) -> Comércio a varejo de motocicletas e motonetas usadas | Y97: 88 | Z97: =LARGE($R$10:$R$1048576,Y97) -> 0 | AA97: =INDEX(S$10:S$1000, MATCH(R97, R$10:R$1000, 0)) -> Guarda-móveis | AB97: =COUNTIF(R$10:R97,R97) -> 80 | AC97: =R97&U97 -> 080 | AD97: =INDEX($S$10:$S$1048576, MATCH(AC97, $V$10:$V$1048576, 0)) -> Comércio a varejo de motocicletas e motonetas usadas | AE97: =Z97 -> 0
M98: =IF(ISBLANK(D98), "", IFERROR(PROPER(TEXT(D98,"mmmm")),"")) | N98: =IF(H98="","",H98) | O98: =IFERROR(RIGHT(N98,LEN(N98)-SEARCH("- ",N98)-1),"") | Q98: ='CNAE_Cód.Atividade Econômica'!B78 -> Comércio a varejo de peças e acessórios novos para motocicletas e motonetas | R98: =COUNTIF($O:$O,Q98) -> 0 | S98: =Q98 -> Comércio a varejo de peças e acessórios novos para motocicletas e motonetas | U98: =COUNTIF(R$10:R98,R98) -> 81 | V98: =R98&U98 -> 081 | W98: =INDEX($S$10:$S$401, MATCH(V98,$V$10:$V$1048576, 0)) -> Comércio a varejo de peças e acessórios novos para motocicletas e motonetas | Y98: 89 | Z98: =LARGE($R$10:$R$1048576,Y98) -> 0 | AA98: =INDEX(S$10:S$1000, MATCH(R98, R$10:R$1000, 0)) -> Guarda-móveis | AB98: =COUNTIF(R$10:R98,R98) -> 81 | AC98: =R98&U98 -> 081 | AD98: =INDEX($S$10:$S$1048576, MATCH(AC98, $V$10:$V$1048576, 0)) -> Comércio a varejo de peças e acessórios novos para motocicletas e motonetas | AE98: =Z98 -> 0
M99: =IF(ISBLANK(D99), "", IFERROR(PROPER(TEXT(D99,"mmmm")),"")) | N99: =IF(H99="","",H99) | O99: =IFERROR(RIGHT(N99,LEN(N99)-SEARCH("- ",N99)-1),"") | Q99: ='CNAE_Cód.Atividade Econômica'!B79 -> Comércio a varejo de peças e acessórios usados para motocicletas e motonetas | R99: =COUNTIF($O:$O,Q99) -> 0 | S99: =Q99 -> Comércio a varejo de peças e acessórios usados para motocicletas e motonetas | U99: =COUNTIF(R$10:R99,R99) -> 82 | V99: =R99&U99 -> 082 | W99: =INDEX($S$10:$S$401, MATCH(V99,$V$10:$V$1048576, 0)) -> Comércio a varejo de peças e acessórios usados para motocicletas e motonetas | Y99: 90 | Z99: =LARGE($R$10:$R$1048576,Y99) -> 0 | AA99: =INDEX(S$10:S$1000, MATCH(R99, R$10:R$1000, 0)) -> Guarda-móveis | AB99: =COUNTIF(R$10:R99,R99) -> 82 | AC99: =R99&U99 -> 082 | AD99: =INDEX($S$10:$S$1048576, MATCH(AC99, $V$10:$V$1048576, 0)) -> Comércio a varejo de peças e acessórios usados para motocicletas e motonetas | AE99: =Z99 -> 0
M100: =IF(ISBLANK(D100), "", IFERROR(PROPER(TEXT(D100,"mmmm")),"")) | N100: =IF(H100="","",H100) | O100: =IFERROR(RIGHT(N100,LEN(N100)-SEARCH("- ",N100)-1),"") | Q100: ='CNAE_Cód.Atividade Econômica'!B80 -> Representantes comerciais e agentes do comércio de motocicletas e motonetas, peças e acessórios | R100: =COUNTIF($O:$O,Q100) -> 0 | S100: =Q100 -> Representantes comerciais e agentes do comércio de motocicletas e motonetas, peças e acessórios | U100: =COUNTIF(R$10:R100,R100) -> 83 | V100: =R100&U100 -> 083 | W100: =INDEX($S$10:$S$401, MATCH(V100,$V$10:$V$1048576, 0)) -> Representantes comerciais e agentes do comércio de motocicletas e motonetas, peças e acessórios | Y100: 91 | Z100: =LARGE($R$10:$R$1048576,Y100) -> 0 | AA100: =INDEX(S$10:S$1000, MATCH(R100, R$10:R$1000, 0)) -> Guarda-móveis | AB100: =COUNTIF(R$10:R100,R100) -> 83 | AC100: =R100&U100 -> 083 | AD100: =INDEX($S$10:$S$1048576, MATCH(AC100, $V$10:$V$1048576, 0)) -> Representantes comerciais e agentes do comércio de motocicletas e motonetas, peças e acessórios | AE100: =Z100 -> 0
... M167: =IF(ISBLANK(D167), "", IFERROR(PROPER(TEXT(D167,"mmmm")),"")) | N167: =IF(H167="","",H167) | O167: =IFERROR(RIGHT(N167,LEN(N167)-SEARCH("- ",N167)-1),"") | Q167: ='CNAE_Cód.Atividade Econômica'!B147 -> Comércio varejista de artigos de viagem | R167: =COUNTIF($O:$O,Q167) -> 0 | S167: =Q167 -> Comércio varejista de artigos de viagem | U167: =COUNTIF(R$10:R167,R167) -> 150 | V167: =R167&U167 -> 0150 | W167: =INDEX($S$10:$S$401, MATCH(V167,$V$10:$V$1048576, 0)) -> Comércio varejista de artigos de viagem | Y167: 158 | Z167: =LARGE($R$10:$R$1048576,Y167) -> 0 | AA167: =INDEX(S$10:S$1000, MATCH(R167, R$10:R$1000, 0)) -> Guarda-móveis | AB167: =COUNTIF(R$10:R167,R167) -> 150 | AC167: =R167&U167 -> 0150 | AD167: =INDEX($S$10:$S$1048576, MATCH(AC167, $V$10:$V$1048576, 0)) -> Comércio varejista de artigos de viagem | AE167: =Z167 -> 0
M168: =IF(ISBLANK(D168), "", IFERROR(PROPER(TEXT(D168,"mmmm")),"")) | N168: =IF(H168="","",H168) | O168: =IFERROR(RIGHT(N168,LEN(N168)-SEARCH("- ",N168)-1),"") | Q168: ='CNAE_Cód.Atividade Econômica'!B154 -> Comércio varejista de produtos saneantes domissanitários | R168: =COUNTIF($O:$O,Q168) -> 0 | S168: =Q168 -> Comércio varejista de produtos saneantes domissanitários | U168: =COUNTIF(R$10:R168,R168) -> 151 | V168: =R168&U168 -> 0151 | W168: =INDEX($S$10:$S$401, MATCH(V168,$V$10:$V$1048576, 0)) -> Comércio varejista de produtos saneantes domissanitários | Y168: 159 | Z168: =LARGE($R$10:$R$1048576,Y168) -> 0 | AA168: =INDEX(S$10:S$1000, MATCH(R168, R$10:R$1000, 0)) -> Guarda-móveis | AB168: =COUNTIF(R$10:R168,R168) -> 151 | AC168: =R168&U168 -> 0151 | AD168: =INDEX($S$10:$S$1048576, MATCH(AC168, $V$10:$V$1048576, 0)) -> Comércio varejista de produtos saneantes domissanitários | AE168: =Z168 -> 0
M169: =IF(ISBLANK(D169), "", IFERROR(PROPER(TEXT(D169,"mmmm")),"")) | N169: =IF(H169="","",H169) | O169: =IFERROR(RIGHT(N169,LEN(N169)-SEARCH("- ",N169)-1),"") | Q169: ='CNAE_Cód.Atividade Econômica'!B155 -> Comércio varejista de fogos de artifício e artigos pirotécnicos | R169: =COUNTIF($O:$O,Q169) -> 0 | S169: =Q169 -> Comércio varejista de fogos de artifício e artigos pirotécnicos | U169: =COUNTIF(R$10:R169,R169) -> 152 | V169: =R169&U169 -> 0152 | W169: =INDEX($S$10:$S$401, MATCH(V169,$V$10:$V$1048576, 0)) -> Comércio varejista de fogos de artifício e artigos pirotécnicos | Y169: 160 | Z169: =LARGE($R$10:$R$1048576,Y169) -> 0 | AA169: =INDEX(S$10:S$1000, MATCH(R169, R$10:R$1000, 0)) -> Guarda-móveis | AB169: =COUNTIF(R$10:R169,R169) -> 152 | AC169: =R169&U169 -> 0152 | AD169: =INDEX($S$10:$S$1048576, MATCH(AC169, $V$10:$V$1048576, 0)) -> Comércio varejista de fogos de artifício e artigos pirotécnicos | AE169: =Z169 -> 0
M170: =IF(ISBLANK(D170), "", IFERROR(PROPER(TEXT(D170,"mmmm")),"")) | N170: =IF(H170="","",H170) | O170: =IFERROR(RIGHT(N170,LEN(N170)-SEARCH("- ",N170)-1),"") | Q170: ='CNAE_Cód.Atividade Econômica'!B156 -> Comércio varejista de equipamentos para escritório | R170: =COUNTIF($O:$O,Q170) -> 0 | S170: =Q170 -> Comércio varejista de equipamentos para escritório | U170: =COUNTIF(R$10:R170,R170) -> 153 | V170: =R170&U170 -> 0153 | W170: =INDEX($S$10:$S$401, MATCH(V170,$V$10:$V$1048576, 0)) -> Comércio varejista de equipamentos para escritório | Y170: 161 | Z170: =LARGE($R$10:$R$1048576,Y170) -> 0 | AA170: =INDEX(S$10:S$1000, MATCH(R170, R$10:R$1000, 0)) -> Guarda-móveis | AB170: =COUNTIF(R$10:R170,R170) -> 153 | AC170: =R170&U170 -> 0153 | AD170: =INDEX($S$10:$S$1048576, MATCH(AC170, $V$10:$V$1048576, 0)) -> Comércio varejista de equipamentos para escritório | AE170: =Z170 -> 0
M171: =IF(ISBLANK(D171), "", IFERROR(PROPER(TEXT(D171,"mmmm")),"")) | N171: =IF(H171="","",H171) | O171: =IFERROR(RIGHT(N171,LEN(N171)-SEARCH("- ",N171)-1),"") | Q171: ='CNAE_Cód.Atividade Econômica'!B157 -> Comércio varejista de artigos fotográficos e para filmagem | R171: =COUNTIF($O:$O,Q171) -> 0 | S171: =Q171 -> Comércio varejista de artigos fotográficos e para filmagem | U171: =COUNTIF(R$10:R171,R171) -> 154 | V171: =R171&U171 -> 0154 | W171: =INDEX($S$10:$S$401, MATCH(V171,$V$10:$V$1048576, 0)) -> Comércio varejista de artigos fotográficos e para filmagem | Y171: 162 | Z171: =LARGE($R$10:$R$1048576,Y171) -> 0 | AA171: =INDEX(S$10:S$1000, MATCH(R171, R$10:R$1000, 0)) -> Guarda-móveis | AB171: =COUNTIF(R$10:R171,R171) -> 154 | AC171: =R171&U171 -> 0154 | AD171: =INDEX($S$10:$S$1048576, MATCH(AC171, $V$10:$V$1048576, 0)) -> Comércio varejista de artigos fotográficos e para filmagem | AE171: =Z171 -> 0
M172: =IF(ISBLANK(D172), "", IFERROR(PROPER(TEXT(D172,"mmmm")),"")) | N172: =IF(H172="","",H172) | O172: =IFERROR(RIGHT(N172,LEN(N172)-SEARCH("- ",N172)-1),"") | Q172: ='CNAE_Cód.Atividade Econômica'!B159 -> Comércio varejista de outros produtos não especificados anteriormente | R172: =COUNTIF($O:$O,Q172) -> 0 | S172: =Q172 -> Comércio varejista de outros produtos não especificados anteriormente | U172: =COUNTIF(R$10:R172,R172) -> 155 | V172: =R172&U172 -> 0155 | W172: =INDEX($S$10:$S$401, MATCH(V172,$V$10:$V$1048576, 0)) -> Comércio varejista de outros produtos não especificados anteriormente | Y172: 163 | Z172: =LARGE($R$10:$R$1048576,Y172) -> 0 | AA172: =INDEX(S$10:S$1000, MATCH(R172, R$10:R$1000, 0)) -> Guarda-móveis | AB172: =COUNTIF(R$10:R172,R172) -> 155 | AC172: =R172&U172 -> 0155 | AD172: =INDEX($S$10:$S$1048576, MATCH(AC172, $V$10:$V$1048576, 0)) -> Comércio varejista de outros produtos não especificados anteriormente | AE172: =Z172 -> 0
M173: =IF(ISBLANK(D173), "", IFERROR(PROPER(TEXT(D173,"mmmm")),"")) | N173: =IF(H173="","",H173) | O173: =IFERROR(RIGHT(N173,LEN(N173)-SEARCH("- ",N173)-1),"") | Q173: ='CNAE_Cód.Atividade Econômica'!B161 -> Serviços de malote não realizados pelo Correio Nacional | R173: =COUNTIF($O:$O,Q173) -> 0 | S173: =Q173 -> Serviços de malote não realizados pelo Correio Nacional | U173: =COUNTIF(R$10:R173,R173) -> 156 | V173: =R173&U173 -> 0156 | W173: =INDEX($S$10:$S$401, MATCH(V173,$V$10:$V$1048576, 0)) -> Serviços de malote não realizados pelo Correio Nacional | Y173: 164 | Z173: =LARGE($R$10:$R$1048576,Y173) -> 0 | AA173: =INDEX(S$10:S$1000, MATCH(R173, R$10:R$1000, 0)) -> Guarda-móveis | AB173: =COUNTIF(R$10:R173,R173) -> 156 | AC173: =R173&U173 -> 0156 | AD173: =INDEX($S$10:$S$1048576, MATCH(AC173, $V$10:$V$1048576, 0)) -> Serviços de malote não realizados pelo Correio Nacional | AE173: =Z173 -> 0
M174: =IF(ISBLANK(D174), "", IFERROR(PROPER(TEXT(D174,"mmmm")),"")) | N174: =IF(H174="","",H174) | O174: =IFERROR(RIGHT(N174,LEN(N174)-SEARCH("- ",N174)-1),"") | Q174: ='CNAE_Cód.Atividade Econômica'!B162 -> Serviços de entrega rápida | R174: =COUNTIF($O:$O,Q174) -> 0 | S174: =Q174 -> Serviços de entrega rápida | U174: =COUNTIF(R$10:R174,R174) -> 157 | V174: =R174&U174 -> 0157 | W174: =INDEX($S$10:$S$401, MATCH(V174,$V$10:$V$1048576, 0)) -> Serviços de entrega rápida | Y174: 165 | Z174: =LARGE($R$10:$R$1048576,Y174) -> 0 | AA174: =INDEX(S$10:S$1000, MATCH(R174, R$10:R$1000, 0)) -> Guarda-móveis | AB174: =COUNTIF(R$10:R174,R174) -> 157 | AC174: =R174&U174 -> 0157 | AD174: =INDEX($S$10:$S$1048576, MATCH(AC174, $V$10:$V$1048576, 0)) -> Serviços de entrega rápida | AE174: =Z174 -> 0
M175: =IF(ISBLANK(D175), "", IFERROR(PROPER(TEXT(D175,"mmmm")),"")) | N175: =IF(H175="","",H175) | O175: =IFERROR(RIGHT(N175,LEN(N175)-SEARCH("- ",N175)-1),"") | Q175: ='CNAE_Cód.Atividade Econômica'!B163 -> Hotéis | R175: =COUNTIF($O:$O,Q175) -> 0 | S175: =Q175 -> Hotéis | U175: =COUNTIF(R$10:R175,R175) -> 158 | V175: =R175&U175 -> 0158 | W175: =INDEX($S$10:$S$401, MATCH(V175,$V$10:$V$1048576, 0)) -> Hotéis | Y175: 166 | Z175: =LARGE($R$10:$R$1048576,Y175) -> 0 | AA175: =INDEX(S$10:S$1000, MATCH(R175, R$10:R$1000, 0)) -> Guarda-móveis | AB175: =COUNTIF(R$10:R175,R175) -> 158 | AC175: =R175&U175 -> 0158 | AD175: =INDEX($S$10:$S$1048576, MATCH(AC175, $V$10:$V$1048576, 0)) -> Hotéis | AE175: =Z175 -> 0
M176: =IF(ISBLANK(D176), "", IFERROR(PROPER(TEXT(D176,"mmmm")),"")) | N176: =IF(H176="","",H176) | O176: =IFERROR(RIGHT(N176,LEN(N176)-SEARCH("- ",N176)-1),"") | Q176: ='CNAE_Cód.Atividade Econômica'!B164 -> Apart-hotéis | R176: =COUNTIF($O:$O,Q176) -> 0 | S176: =Q176 -> Apart-hotéis | U176: =COUNTIF(R$10:R176,R176) -> 159 | V176: =R176&U176 -> 0159 | W176: =INDEX($S$10:$S$401, MATCH(V176,$V$10:$V$1048576, 0)) -> Apart-hotéis | Y176: 167 | Z176: =LARGE($R$10:$R$1048576,Y176) -> 0 | AA176: =INDEX(S$10:S$1000, MATCH(R176, R$10:R$1000, 0)) -> Guarda-móveis | AB176: =COUNTIF(R$10:R176,R176) -> 159 | AC176: =R176&U176 -> 0159 | AD176: =INDEX($S$10:$S$1048576, MATCH(AC176, $V$10:$V$1048576, 0)) -> Apart-hotéis | AE176: =Z176 -> 0
M177: =IF(ISBLANK(D177), "", IFERROR(PROPER(TEXT(D177,"mmmm")),"")) | N177: =IF(H177="","",H177) | O177: =IFERROR(RIGHT(N177,LEN(N177)-SEARCH("- ",N177)-1),"") | Q177: ='CNAE_Cód.Atividade Econômica'!B165 -> Motéis | R177: =COUNTIF($O:$O,Q177) -> 0 | S177: =Q177 -> Motéis | U177: =COUNTIF(R$10:R177,R177) -> 160 | V177: =R177&U177 -> 0160 | W177: =INDEX($S$10:$S$401, MATCH(V177,$V$10:$V$1048576, 0)) -> Motéis | Y177: 168 | Z177: =LARGE($R$10:$R$1048576,Y177) -> 0 | AA177: =INDEX(S$10:S$1000, MATCH(R177, R$10:R$1000, 0)) -> Guarda-móveis | AB177: =COUNTIF(R$10:R177,R177) -> 160 | AC177: =R177&U177 -> 0160 | AD177: =INDEX($S$10:$S$1048576, MATCH(AC177, $V$10:$V$1048576, 0)) -> Motéis | AE177: =Z177 -> 0
M178: =IF(ISBLANK(D178), "", IFERROR(PROPER(TEXT(D178,"mmmm")),"")) | N178: =IF(H178="","",H178) | O178: =IFERROR(RIGHT(N178,LEN(N178)-SEARCH("- ",N178)-1),"") | Q178: ='CNAE_Cód.Atividade Econômica'!B166 -> Albergues, exceto assistenciais | R178: =COUNTIF($O:$O,Q178) -> 0 | S178: =Q178 -> Albergues, exceto assistenciais | U178: =COUNTIF(R$10:R178,R178) -> 161 | V178: =R178&U178 -> 0161 | W178: =INDEX($S$10:$S$401, MATCH(V178,$V$10:$V$1048576, 0)) -> Albergues, exceto assistenciais | Y178: 169 | Z178: =LARGE($R$10:$R$1048576,Y178) -> 0 | AA178: =INDEX(S$10:S$1000, MATCH(R178, R$10:R$1000, 0)) -> Guarda-móveis | AB178: =COUNTIF(R$10:R178,R178) -> 161 | AC178: =R178&U178 -> 0161 | AD178: =INDEX($S$10:$S$1048576, MATCH(AC178, $V$10:$V$1048576, 0)) -> Albergues, exceto assistenciais | AE178: =Z178 -> 0
M179: =IF(ISBLANK(D179), "", IFERROR(PROPER(TEXT(D179,"mmmm")),"")) | N179: =IF(H179="","",H179) | O179: =IFERROR(RIGHT(N179,LEN(N179)-SEARCH("- ",N179)-1),"") | Q179: ='CNAE_Cód.Atividade Econômica'!B168 -> Pensões (alojamento) | R179: =COUNTIF($O:$O,Q179) -> 0 | S179: =Q179 -> Pensões (alojamento) | U179: =COUNTIF(R$10:R179,R179) -> 162 | V179: =R179&U179 -> 0162 | W179: =INDEX($S$10:$S$401, MATCH(V179,$V$10:$V$1048576, 0)) -> Pensões (alojamento) | Y179: 170 | Z179: =LARGE($R$10:$R$1048576,Y179) -> 0 | AA179: =INDEX(S$10:S$1000, MATCH(R179, R$10:R$1000, 0)) -> Guarda-móveis | AB179: =COUNTIF(R$10:R179,R179) -> 162 | AC179: =R179&U179 -> 0162 | AD179: =INDEX($S$10:$S$1048576, MATCH(AC179, $V$10:$V$1048576, 0)) -> Pensões (alojamento) | AE179: =Z179 -> 0
M180: =IF(ISBLANK(D180), "", IFERROR(PROPER(TEXT(D180,"mmmm")),"")) | N180: =IF(H180="","",H180) | O180: =IFERROR(RIGHT(N180,LEN(N180)-SEARCH("- ",N180)-1),"") | Q180: ='CNAE_Cód.Atividade Econômica'!B169 -> Outros alojamentos não especificados anteriormente | R180: =COUNTIF($O:$O,Q180) -> 0 | S180: =Q180 -> Outros alojamentos não especificados anteriormente | U180: =COUNTIF(R$10:R180,R180) -> 163 | V180: =R180&U180 -> 0163 | W180: =INDEX($S$10:$S$401, MATCH(V180,$V$10:$V$1048576, 0)) -> Outros alojamentos não especificados anteriormente | Y180: 171 | Z180: =LARGE($R$10:$R$1048576,Y180) -> 0 | AA180: =INDEX(S$10:S$1000, MATCH(R180, R$10:R$1000, 0)) -> Guarda-móveis | AB180: =COUNTIF(R$10:R180,R180) -> 163 | AC180: =R180&U180 -> 0163 | AD180: =INDEX($S$10:$S$1048576, MATCH(AC180, $V$10:$V$1048576, 0)) -> Outros alojamentos não especificados anteriormente | AE180: =Z180 -> 0
M181: =IF(ISBLANK(D181), "", IFERROR(PROPER(TEXT(D181,"mmmm")),"")) | N181: =IF(H181="","",H181) | O181: =IFERROR(RIGHT(N181,LEN(N181)-SEARCH("- ",N181)-1),"") | Q181: ='CNAE_Cód.Atividade Econômica'!B170 -> Restaurantes e similares | R181: =COUNTIF($O:$O,Q181) -> 0 | S181: =Q181 -> Restaurantes e similares | U181: =COUNTIF(R$10:R181,R181) -> 164 | V181: =R181&U181 -> 0164 | W181: =INDEX($S$10:$S$401, MATCH(V181,$V$10:$V$1048576, 0)) -> Restaurantes e similares | Y181: 172 | Z181: =LARGE($R$10:$R$1048576,Y181) -> 0 | AA181: =INDEX(S$10:S$1000, MATCH(R181, R$10:R$1000, 0)) -> Guarda-móveis | AB181: =COUNTIF(R$10:R181,R181) -> 164 | AC181: =R181&U181 -> 0164 | AD181: =INDEX($S$10:$S$1048576, MATCH(AC181, $V$10:$V$1048576, 0)) -> Restaurantes e similares | AE181: =Z181 -> 0
M182: =IF(ISBLANK(D182), "", IFERROR(PROPER(TEXT(D182,"mmmm")),"")) | N182: =IF(H182="","",H182) | O182: =IFERROR(RIGHT(N182,LEN(N182)-SEARCH("- ",N182)-1),"") | Q182: ='CNAE_Cód.Atividade Econômica'!B171 -> Lanchonetes, casas de chá, de sucos e similares | R182: =COUNTIF($O:$O,Q182) -> 0 | S182: =Q182 -> Lanchonetes, casas de chá, de sucos e similares | U182: =COUNTIF(R$10:R182,R182) -> 165 | V182: =R182&U182 -> 0165 | W182: =INDEX($S$10:$S$401, MATCH(V182,$V$10:$V$1048576, 0)) -> Lanchonetes, casas de chá, de sucos e similares | Y182: 173 | Z182: =LARGE($R$10:$R$1048576,Y182) -> 0 | AA182: =INDEX(S$10:S$1000, MATCH(R182, R$10:R$1000, 0)) -> Guarda-móveis | AB182: =COUNTIF(R$10:R182,R182) -> 165 | AC182: =R182&U182 -> 0165 | AD182: =INDEX($S$10:$S$1048576, MATCH(AC182, $V$10:$V$1048576, 0)) -> Lanchonetes, casas de chá, de sucos e similares | AE182: =Z182 -> 0
M183: =IF(ISBLANK(D183), "", IFERROR(PROPER(TEXT(D183,"mmmm")),"")) | N183: =IF(H183="","",H183) | O183: =IFERROR(RIGHT(N183,LEN(N183)-SEARCH("- ",N183)-1),"") | Q183: ='CNAE_Cód.Atividade Econômica'!B172 -> Bares e outros estabelecimentos especializados em servir bebidas, sem entretenimento | R183: =COUNTIF($O:$O,Q183) -> 0 | S183: =Q183 -> Bares e outros estabelecimentos especializados em servir bebidas, sem entretenimento | U183: =COUNTIF(R$10:R183,R183) -> 166 | V183: =R183&U183 -> 0166 | W183: =INDEX($S$10:$S$401, MATCH(V183,$V$10:$V$1048576, 0)) -> Bares e outros estabelecimentos especializados em servir bebidas, sem entretenimento | Y183: 174 | Z183: =LARGE($R$10:$R$1048576,Y183) -> 0 | AA183: =INDEX(S$10:S$1000, MATCH(R183, R$10:R$1000, 0)) -> Guarda-móveis | AB183: =COUNTIF(R$10:R183,R183) -> 166 | AC183: =R183&U183 -> 0166 | AD183: =INDEX($S$10:$S$1048576, MATCH(AC183, $V$10:$V$1048576, 0)) -> Bares e outros estabelecimentos especializados em servir bebidas, sem entretenimento | AE183: =Z183 -> 0
M184: =IF(ISBLANK(D184), "", IFERROR(PROPER(TEXT(D184,"mmmm")),"")) | N184: =IF(H184="","",H184) | O184: =IFERROR(RIGHT(N184,LEN(N184)-SEARCH("- ",N184)-1),"") | Q184: ='CNAE_Cód.Atividade Econômica'!B173 -> Fornecimento de alimentos preparados preponderantemente para empresas | R184: =COUNTIF($O:$O,Q184) -> 0 | S184: =Q184 -> Fornecimento de alimentos preparados preponderantemente para empresas | U184: =COUNTIF(R$10:R184,R184) -> 167 | V184: =R184&U184 -> 0167 | W184: =INDEX($S$10:$S$401, MATCH(V184,$V$10:$V$1048576, 0)) -> Fornecimento de alimentos preparados preponderantemente para empresas | Y184: 175 | Z184: =LARGE($R$10:$R$1048576,Y184) -> 0 | AA184: =INDEX(S$10:S$1000, MATCH(R184, R$10:R$1000, 0)) -> Guarda-móveis | AB184: =COUNTIF(R$10:R184,R184) -> 167 | AC184: =R184&U184 -> 0167 | AD184: =INDEX($S$10:$S$1048576, MATCH(AC184, $V$10:$V$1048576, 0)) -> Fornecimento de alimentos preparados preponderantemente para empresas | AE184: =Z184 -> 0
M185: =IF(ISBLANK(D185), "", IFERROR(PROPER(TEXT(D185,"mmmm")),"")) | N185: =IF(H185="","",H185) | O185: =IFERROR(RIGHT(N185,LEN(N185)-SEARCH("- ",N185)-1),"") | Q185: ='CNAE_Cód.Atividade Econômica'!B174 -> Serviços de alimentação para eventos e recepções – bufê | R185: =COUNTIF($O:$O,Q185) -> 0 | S185: =Q185 -> Serviços de alimentação para eventos e recepções – bufê | U185: =COUNTIF(R$10:R185,R185) -> 168 | V185: =R185&U185 -> 0168 | W185: =INDEX($S$10:$S$401, MATCH(V185,$V$10:$V$1048576, 0)) -> Serviços de alimentação para eventos e recepções – bufê | Y185: 176 | Z185: =LARGE($R$10:$R$1048576,Y185) -> 0 | AA185: =INDEX(S$10:S$1000, MATCH(R185, R$10:R$1000, 0)) -> Guarda-móveis | AB185: =COUNTIF(R$10:R185,R185) -> 168 | AC185: =R185&U185 -> 0168 | AD185: =INDEX($S$10:$S$1048576, MATCH(AC185, $V$10:$V$1048576, 0)) -> Serviços de alimentação para eventos e recepções – bufê | AE185: =Z185 -> 0
M186: =IF(ISBLANK(D186), "", IFERROR(PROPER(TEXT(D186,"mmmm")),"")) | N186: =IF(H186="","",H186) | O186: =IFERROR(RIGHT(N186,LEN(N186)-SEARCH("- ",N186)-1),"") | Q186: ='CNAE_Cód.Atividade Econômica'!B175 -> Cantinas – serviços de alimentação privativos | R186: =COUNTIF($O:$O,Q186) -> 0 | S186: =Q186 -> Cantinas – serviços de alimentação privativos | U186: =COUNTIF(R$10:R186,R186) -> 169 | V186: =R186&U186 -> 0169 | W186: =INDEX($S$10:$S$401, MATCH(V186,$V$10:$V$1048576, 0)) -> Cantinas – serviços de alimentação privativos | Y186: 177 | Z186: =LARGE($R$10:$R$1048576,Y186) -> 0 | AA186: =INDEX(S$10:S$1000, MATCH(R186, R$10:R$1000, 0)) -> Guarda-móveis | AB186: =COUNTIF(R$10:R186,R186) -> 169 | AC186: =R186&U186 -> 0169 | AD186: =INDEX($S$10:$S$1048576, MATCH(AC186, $V$10:$V$1048576, 0)) -> Cantinas – serviços de alimentação privativos | AE186: =Z186 -> 0
M187: =IF(ISBLANK(D187), "", IFERROR(PROPER(TEXT(D187,"mmmm")),"")) | N187: =IF(H187="","",H187) | O187: =IFERROR(RIGHT(N187,LEN(N187)-SEARCH("- ",N187)-1),"") | Q187: ='CNAE_Cód.Atividade Econômica'!B176 -> Fornecimento de alimentos preparados preponderantemente para consumo domiciliar | R187: =COUNTIF($O:$O,Q187) -> 0 | S187: =Q187 -> Fornecimento de alimentos preparados preponderantemente para consumo domiciliar | U187: =COUNTIF(R$10:R187,R187) -> 170 | V187: =R187&U187 -> 0170 | W187: =INDEX($S$10:$S$401, MATCH(V187,$V$10:$V$1048576, 0)) -> Fornecimento de alimentos preparados preponderantemente para consumo domiciliar | Y187: 178 | Z187: =LARGE($R$10:$R$1048576,Y187) -> 0 | AA187: =INDEX(S$10:S$1000, MATCH(R187, R$10:R$1000, 0)) -> Guarda-móveis | AB187: =COUNTIF(R$10:R187,R187) -> 170 | AC187: =R187&U187 -> 0170 | AD187: =INDEX($S$10:$S$1048576, MATCH(AC187, $V$10:$V$1048576, 0)) -> Fornecimento de alimentos preparados preponderantemente para consumo domiciliar | AE187: =Z187 -> 0
M188: =IF(ISBLANK(D188), "", IFERROR(PROPER(TEXT(D188,"mmmm")),"")) | N188: =IF(H188="","",H188) | O188: =IFERROR(RIGHT(N188,LEN(N188)-SEARCH("- ",N188)-1),"") | Q188: ='CNAE_Cód.Atividade Econômica'!B177 -> Edição de livros | R188: =COUNTIF($O:$O,Q188) -> 0 | S188: =Q188 -> Edição de livros | U188: =COUNTIF(R$10:R188,R188) -> 171 | V188: =R188&U188 -> 0171 | W188: =INDEX($S$10:$S$401, MATCH(V188,$V$10:$V$1048576, 0)) -> Edição de livros | Y188: 179 | Z188: =LARGE($R$10:$R$1048576,Y188) -> 0 | AA188: =INDEX(S$10:S$1000, MATCH(R188, R$10:R$1000, 0)) -> Guarda-móveis | AB188: =COUNTIF(R$10:R188,R188) -> 171 | AC188: =R188&U188 -> 0171 | AD188: =INDEX($S$10:$S$1048576, MATCH(AC188, $V$10:$V$1048576, 0)) -> Edição de livros | AE188: =Z188 -> 0
M189: =IF(ISBLANK(D189), "", IFERROR(PROPER(TEXT(D189,"mmmm")),"")) | N189: =IF(H189="","",H189) | O189: =IFERROR(RIGHT(N189,LEN(N189)-SEARCH("- ",N189)-1),"") | Q189: ='CNAE_Cód.Atividade Econômica'!B178 -> Edição de jornais diários | R189: =COUNTIF($O:$O,Q189) -> 0 | S189: =Q189 -> Edição de jornais diários | U189: =COUNTIF(R$10:R189,R189) -> 172 | V189: =R189&U189 -> 0172 | W189: =INDEX($S$10:$S$401, MATCH(V189,$V$10:$V$1048576, 0)) -> Edição de jornais diários | Y189: 180 | Z189: =LARGE($R$10:$R$1048576,Y189) -> 0 | AA189: =INDEX(S$10:S$1000, MATCH(R189, R$10:R$1000, 0)) -> Guarda-móveis | AB189: =COUNTIF(R$10:R189,R189) -> 172 | AC189: =R189&U189 -> 0172 | AD189: =INDEX($S$10:$S$1048576, MATCH(AC189, $V$10:$V$1048576, 0)) -> Edição de jornais diários | AE189: =Z189 -> 0
M190: =IF(ISBLANK(D190), "", IFERROR(PROPER(TEXT(D190,"mmmm")),"")) | N190: =IF(H190="","",H190) | O190: =IFERROR(RIGHT(N190,LEN(N190)-SEARCH("- ",N190)-1),"") | Q190: ='CNAE_Cód.Atividade Econômica'!B179 -> Edição de jornais não diários | R190: =COUNTIF($O:$O,Q190) -> 0 | S190: =Q190 -> Edição de jornais não diários | U190: =COUNTIF(R$10:R190,R190) -> 173 | V190: =R190&U190 -> 0173 | W190: =INDEX($S$10:$S$401, MATCH(V190,$V$10:$V$1048576, 0)) -> Edição de jornais não diários | Y190: 181 | Z190: =LARGE($R$10:$R$1048576,Y190) -> 0 | AA190: =INDEX(S$10:S$1000, MATCH(R190, R$10:R$1000, 0)) -> Guarda-móveis | AB190: =COUNTIF(R$10:R190,R190) -> 173 | AC190: =R190&U190 -> 0173 | AD190: =INDEX($S$10:$S$1048576, MATCH(AC190, $V$10:$V$1048576, 0)) -> Edição de jornais não diários | AE190: =Z190 -> 0
... M396: =IF(ISBLANK(D396), "", IFERROR(PROPER(TEXT(D396,"mmmm")),"")) | N396: =IF(H396="","",H396) | O396: =IFERROR(RIGHT(N396,LEN(N396)-SEARCH("- ",N396)-1),"") | Q396: ='CNAE_Cód.Atividade Econômica'!B385 -> Cabeleireiros, manicure e pedicure | R396: =COUNTIF($O:$O,Q396) -> 0 | S396: =Q396 -> Cabeleireiros, manicure e pedicure | U396: =COUNTIF(R$10:R396,R396) -> 379 | V396: =R396&U396 -> 0379 | W396: =INDEX($S$10:$S$401, MATCH(V396,$V$10:$V$1048576, 0)) -> Cabeleireiros, manicure e pedicure | Y396: 387 | Z396: =LARGE($R$10:$R$1048576,Y396) -> 0 | AA396: =INDEX(S$10:S$1000, MATCH(R396, R$10:R$1000, 0)) -> Guarda-móveis | AB396: =COUNTIF(R$10:R396,R396) -> 379 | AC396: =R396&U396 -> 0379 | AD396: =INDEX($S$10:$S$1048576, MATCH(AC396, $V$10:$V$1048576, 0)) -> Cabeleireiros, manicure e pedicure | AE396: =Z396 -> 0
M397: =IF(ISBLANK(D397), "", IFERROR(PROPER(TEXT(D397,"mmmm")),"")) | N397: =IF(H397="","",H397) | O397: =IFERROR(RIGHT(N397,LEN(N397)-SEARCH("- ",N397)-1),"") | Q397: ='CNAE_Cód.Atividade Econômica'!B387 -> Agências matrimoniais | R397: =COUNTIF($O:$O,Q397) -> 0 | S397: =Q397 -> Agências matrimoniais | U397: =COUNTIF(R$10:R397,R397) -> 380 | V397: =R397&U397 -> 0380 | W397: =INDEX($S$10:$S$401, MATCH(V397,$V$10:$V$1048576, 0)) -> Agências matrimoniais | Y397: 388 | Z397: =LARGE($R$10:$R$1048576,Y397) -> 0 | AA397: =INDEX(S$10:S$1000, MATCH(R397, R$10:R$1000, 0)) -> Guarda-móveis | AB397: =COUNTIF(R$10:R397,R397) -> 380 | AC397: =R397&U397 -> 0380 | AD397: =INDEX($S$10:$S$1048576, MATCH(AC397, $V$10:$V$1048576, 0)) -> Agências matrimoniais | AE397: =Z397 -> 0
M398: =IF(ISBLANK(D398), "", IFERROR(PROPER(TEXT(D398,"mmmm")),"")) | N398: =IF(H398="","",H398) | O398: =IFERROR(RIGHT(N398,LEN(N398)-SEARCH("- ",N398)-1),"") | Q398: ='CNAE_Cód.Atividade Econômica'!B390 -> Alojamento de animais domésticos | R398: =COUNTIF($O:$O,Q398) -> 0 | S398: =Q398 -> Alojamento de animais domésticos | U398: =COUNTIF(R$10:R398,R398) -> 381 | V398: =R398&U398 -> 0381 | W398: =INDEX($S$10:$S$401, MATCH(V398,$V$10:$V$1048576, 0)) -> Alojamento de animais domésticos | Y398: 389 | Z398: =LARGE($R$10:$R$1048576,Y398) -> 0 | AA398: =INDEX(S$10:S$1000, MATCH(R398, R$10:R$1000, 0)) -> Guarda-móveis | AB398: =COUNTIF(R$10:R398,R398) -> 381 | AC398: =R398&U398 -> 0381 | AD398: =INDEX($S$10:$S$1048576, MATCH(AC398, $V$10:$V$1048576, 0)) -> Alojamento de animais domésticos | AE398: =Z398 -> 0
M399: =IF(ISBLANK(D399), "", IFERROR(PROPER(TEXT(D399,"mmmm")),"")) | N399: =IF(H399="","",H399) | O399: =IFERROR(RIGHT(N399,LEN(N399)-SEARCH("- ",N399)-1),"") | Q399: ='CNAE_Cód.Atividade Econômica'!B391 -> Higiene e embelezamento de animais domésticos | R399: =COUNTIF($O:$O,Q399) -> 0 | S399: =Q399 -> Higiene e embelezamento de animais domésticos | U399: =COUNTIF(R$10:R399,R399) -> 382 | V399: =R399&U399 -> 0382 | W399: =INDEX($S$10:$S$401, MATCH(V399,$V$10:$V$1048576, 0)) -> Higiene e embelezamento de animais domésticos | Y399: 390 | Z399: =LARGE($R$10:$R$1048576,Y399) -> 0 | AA399: =INDEX(S$10:S$1000, MATCH(R399, R$10:R$1000, 0)) -> Guarda-móveis | AB399: =COUNTIF(R$10:R399,R399) -> 382 | AC399: =R399&U399 -> 0382 | AD399: =INDEX($S$10:$S$1048576, MATCH(AC399, $V$10:$V$1048576, 0)) -> Higiene e embelezamento de animais domésticos | AE399: =Z399 -> 0
M400: =IF(ISBLANK(D400), "", IFERROR(PROPER(TEXT(D400,"mmmm")),"")) | N400: =IF(H400="","",H400) | O400: =IFERROR(RIGHT(N400,LEN(N400)-SEARCH("- ",N400)-1),"") | Q400: ='CNAE_Cód.Atividade Econômica'!B392 -> Outras atividades de serviços pessoais não especificadas anteriormente | R400: =COUNTIF($O:$O,Q400) -> 0 | S400: =Q400 -> Outras atividades de serviços pessoais não especificadas anteriormente | U400: =COUNTIF(R$10:R400,R400) -> 383 | V400: =R400&U400 -> 0383 | W400: =INDEX($S$10:$S$401, MATCH(V400,$V$10:$V$1048576, 0)) -> Outras atividades de serviços pessoais não especificadas anteriormente | Y400: 391 | Z400: =LARGE($R$10:$R$1048576,Y400) -> 0 | AA400: =INDEX(S$10:S$1000, MATCH(R400, R$10:R$1000, 0)) -> Guarda-móveis | AB400: =COUNTIF(R$10:R400,R400) -> 383 | AC400: =R400&U400 -> 0383 | AD400: =INDEX($S$10:$S$1048576, MATCH(AC400, $V$10:$V$1048576, 0)) -> Outras atividades de serviços pessoais não especificadas anteriormente | AE400: =Z400 -> 0
M401: =IF(ISBLANK(D401), "", IFERROR(PROPER(TEXT(D401,"mmmm")),"")) | N401: =IF(H401="","",H401) | O401: =IFERROR(RIGHT(N401,LEN(N401)-SEARCH("- ",N401)-1),"") | R401: =COUNTIF($O:$O,Q401) -> 0 | S401: =Q401 -> 0 | U401: =COUNTIF(R$10:R401,R401) -> 384 | V401: =R401&U401 -> 0384 | W401: =INDEX($S$10:$S$401, MATCH(V401,$V$10:$V$1048576, 0)) -> 0 | Y401: 392 | Z401: =LARGE($R$10:$R$1048576,Y401) -> 0 | AA401: =INDEX(S$10:S$1000, MATCH(R401, R$10:R$1000, 0)) -> Guarda-móveis | AB401: =COUNTIF(R$10:R401,R401) -> 384 | AC401: =R401&U401 -> 0384 | AD401: =INDEX($S$10:$S$1048576, MATCH(AC401, $V$10:$V$1048576, 0)) -> 0 | AE401: =Z401 -> 0
M402: =IF(ISBLANK(D402), "", IFERROR(PROPER(TEXT(D402,"mmmm")),"")) | N402: =IF(H402="","",H402) | O402: =IFERROR(RIGHT(N402,LEN(N402)-SEARCH("- ",N402)-1),"") | R402: =COUNTIF($O:$O,Q402) -> 0 | S402: =Q402 -> 0 | U402: =COUNTIF(R$10:R402,R402) -> 385 | V402: =R402&U402 -> 0385 | W402: =INDEX($S$10:$S$401, MATCH(V402,$V$10:$V$1048576, 0)) -> #REF! | Y402: 393 | Z402: =LARGE($R$10:$R$1048576,Y402) -> 0 | AA402: =INDEX(S$10:S$1000, MATCH(R402, R$10:R$1000, 0)) -> Guarda-móveis | AB402: =COUNTIF(R$10:R402,R402) -> 385 | AC402: =R402&U402 -> 0385 | AD402: =INDEX($S$10:$S$1048576, MATCH(AC402, $V$10:$V$1048576, 0)) -> 0 | AE402: =Z402 -> 0
M403: =IF(ISBLANK(D403), "", IFERROR(PROPER(TEXT(D403,"mmmm")),"")) | N403: =IF(H403="","",H403) | O403: =IFERROR(RIGHT(N403,LEN(N403)-SEARCH("- ",N403)-1),"") | R403: =COUNTIF($O:$O,Q403) -> 0 | S403: =Q403 -> 0 | U403: =COUNTIF(R$10:R403,R403) -> 386 | V403: =R403&U403 -> 0386 | W403: =INDEX($S$10:$S$401, MATCH(V403,$V$10:$V$1048576, 0)) -> #REF! | Y403: 394 | Z403: =LARGE($R$10:$R$1048576,Y403) -> 0 | AA403: =INDEX(S$10:S$1000, MATCH(R403, R$10:R$1000, 0)) -> Guarda-móveis | AB403: =COUNTIF(R$10:R403,R403) -> 386 | AC403: =R403&U403 -> 0386 | AD403: =INDEX($S$10:$S$1048576, MATCH(AC403, $V$10:$V$1048576, 0)) -> 0 | AE403: =Z403 -> 0
M404: =IF(ISBLANK(D404), "", IFERROR(PROPER(TEXT(D404,"mmmm")),"")) | N404: =IF(H404="","",H404) | O404: =IFERROR(RIGHT(N404,LEN(N404)-SEARCH("- ",N404)-1),"") | R404: =COUNTIF($O:$O,Q404) -> 0 | S404: =Q404 -> 0 | U404: =COUNTIF(R$10:R404,R404) -> 387 | V404: =R404&U404 -> 0387 | W404: =INDEX($S$10:$S$401, MATCH(V404,$V$10:$V$1048576, 0)) -> #REF! | Y404: 395 | Z404: =LARGE($R$10:$R$1048576,Y404) -> 0 | AA404: =INDEX(S$10:S$1000, MATCH(R404, R$10:R$1000, 0)) -> Guarda-móveis | AB404: =COUNTIF(R$10:R404,R404) -> 387 | AC404: =R404&U404 -> 0387 | AD404: =INDEX($S$10:$S$1048576, MATCH(AC404, $V$10:$V$1048576, 0)) -> 0 | AE404: =Z404 -> 0
M405: =IF(ISBLANK(D405), "", IFERROR(PROPER(TEXT(D405,"mmmm")),"")) | N405: =IF(H405="","",H405) | O405: =IFERROR(RIGHT(N405,LEN(N405)-SEARCH("- ",N405)-1),"") | R405: =COUNTIF($O:$O,Q405) -> 0 | S405: =Q405 -> 0 | U405: =COUNTIF(R$10:R405,R405) -> 388 | V405: =R405&U405 -> 0388 | W405: =INDEX($S$10:$S$401, MATCH(V405,$V$10:$V$1048576, 0)) -> #REF! | Y405: 396 | Z405: =LARGE($R$10:$R$1048576,Y405) -> 0 | AA405: =INDEX(S$10:S$1000, MATCH(R405, R$10:R$1000, 0)) -> Guarda-móveis | AB405: =COUNTIF(R$10:R405,R405) -> 388 | AC405: =R405&U405 -> 0388 | AD405: =INDEX($S$10:$S$1048576, MATCH(AC405, $V$10:$V$1048576, 0)) -> 0 | AE405: =Z405 -> 0
M406: =IF(ISBLANK(D406), "", IFERROR(PROPER(TEXT(D406,"mmmm")),"")) | N406: =IF(H406="","",H406) | O406: =IFERROR(RIGHT(N406,LEN(N406)-SEARCH("- ",N406)-1),"") | R406: =COUNTIF($O:$O,Q406) -> 0 | S406: =Q406 -> 0 | U406: =COUNTIF(R$10:R406,R406) -> 389 | V406: =R406&U406 -> 0389 | W406: =INDEX($S$10:$S$401, MATCH(V406,$V$10:$V$1048576, 0)) -> #REF! | Y406: 397 | Z406: =LARGE($R$10:$R$1048576,Y406) -> 0 | AA406: =INDEX(S$10:S$1000, MATCH(R406, R$10:R$1000, 0)) -> Guarda-móveis | AB406: =COUNTIF(R$10:R406,R406) -> 389 | AC406: =R406&U406 -> 0389 | AD406: =INDEX($S$10:$S$1048576, MATCH(AC406, $V$10:$V$1048576, 0)) -> 0 | AE406: =Z406 -> 0
M407: =IF(ISBLANK(D407), "", IFERROR(PROPER(TEXT(D407,"mmmm")),"")) | N407: =IF(H407="","",H407) | O407: =IFERROR(RIGHT(N407,LEN(N407)-SEARCH("- ",N407)-1),"") | R407: =COUNTIF($O:$O,Q407) -> 0 | S407: =Q407 -> 0 | U407: =COUNTIF(R$10:R407,R407) -> 390 | V407: =R407&U407 -> 0390 | W407: =INDEX($S$10:$S$401, MATCH(V407,$V$10:$V$1048576, 0)) -> #REF! | Y407: 398 | Z407: =LARGE($R$10:$R$1048576,Y407) -> 0 | AA407: =INDEX(S$10:S$1000, MATCH(R407, R$10:R$1000, 0)) -> Guarda-móveis | AB407: =COUNTIF(R$10:R407,R407) -> 390 | AC407: =R407&U407 -> 0390 | AD407: =INDEX($S$10:$S$1048576, MATCH(AC407, $V$10:$V$1048576, 0)) -> 0 | AE407: =Z407 -> 0
M408: =IF(ISBLANK(D408), "", IFERROR(PROPER(TEXT(D408,"mmmm")),"")) | N408: =IF(H408="","",H408) | O408: =IFERROR(RIGHT(N408,LEN(N408)-SEARCH("- ",N408)-1),"") | R408: =COUNTIF($O:$O,Q408) -> 0 | S408: =Q408 -> 0 | U408: =COUNTIF(R$10:R408,R408) -> 391 | V408: =R408&U408 -> 0391 | W408: =INDEX($S$10:$S$401, MATCH(V408,$V$10:$V$1048576, 0)) -> #REF! | Y408: 399 | Z408: =LARGE($R$10:$R$1048576,Y408) -> 0 | AA408: =INDEX(S$10:S$1000, MATCH(R408, R$10:R$1000, 0)) -> Guarda-móveis | AB408: =COUNTIF(R$10:R408,R408) -> 391 | AC408: =R408&U408 -> 0391 | AD408: =INDEX($S$10:$S$1048576, MATCH(AC408, $V$10:$V$1048576, 0)) -> 0 | AE408: =Z408 -> 0
M409: =IF(ISBLANK(D409), "", IFERROR(PROPER(TEXT(D409,"mmmm")),"")) | N409: =IF(H409="","",H409) | O409: =IFERROR(RIGHT(N409,LEN(N409)-SEARCH("- ",N409)-1),"") | R409: =COUNTIF($O:$O,Q409) -> 0 | S409: =Q409 -> 0 | U409: =COUNTIF(R$10:R409,R409) -> 392 | V409: =R409&U409 -> 0392 | W409: =INDEX($S$10:$S$401, MATCH(V409,$V$10:$V$1048576, 0)) -> #REF! | Y409: 400 | Z409: =LARGE($R$10:$R$1048576,Y409) -> 0 | AA409: =INDEX(S$10:S$1000, MATCH(R409, R$10:R$1000, 0)) -> Guarda-móveis | AB409: =COUNTIF(R$10:R409,R409) -> 392 | AC409: =R409&U409 -> 0392 | AD409: =INDEX($S$10:$S$1048576, MATCH(AC409, $V$10:$V$1048576, 0)) -> 0 | AE409: =Z409 -> 0
M410: =IF(ISBLANK(D410), "", IFERROR(PROPER(TEXT(D410,"mmmm")),"")) | N410: =IF(H410="","",H410) | O410: =IFERROR(RIGHT(N410,LEN(N410)-SEARCH("- ",N410)-1),"") | R410: =COUNTIF($O:$O,Q410) -> 0 | S410: =Q410 -> 0 | U410: =COUNTIF(R$10:R410,R410) -> 393 | V410: =R410&U410 -> 0393 | W410: =INDEX($S$10:$S$401, MATCH(V410,$V$10:$V$1048576, 0)) -> #REF! | Y410: 401 | Z410: =LARGE($R$10:$R$1048576,Y410) -> 0 | AA410: =INDEX(S$10:S$1000, MATCH(R410, R$10:R$1000, 0)) -> Guarda-móveis | AB410: =COUNTIF(R$10:R410,R410) -> 393 | AC410: =R410&U410 -> 0393 | AD410: =INDEX($S$10:$S$1048576, MATCH(AC410, $V$10:$V$1048576, 0)) -> 0 | AE410: =Z410 -> 0
M411: =IF(ISBLANK(D411), "", IFERROR(PROPER(TEXT(D411,"mmmm")),"")) | N411: =IF(H411="","",H411) | O411: =IFERROR(RIGHT(N411,LEN(N411)-SEARCH("- ",N411)-1),"") | R411: =COUNTIF($O:$O,Q411) -> 0 | S411: =Q411 -> 0 | U411: =COUNTIF(R$10:R411,R411) -> 394 | V411: =R411&U411 -> 0394 | W411: =INDEX($S$10:$S$401, MATCH(V411,$V$10:$V$1048576, 0)) -> #REF! | Y411: 402 | Z411: =LARGE($R$10:$R$1048576,Y411) -> 0 | AA411: =INDEX(S$10:S$1000, MATCH(R411, R$10:R$1000, 0)) -> Guarda-móveis | AB411: =COUNTIF(R$10:R411,R411) -> 394 | AC411: =R411&U411 -> 0394 | AD411: =INDEX($S$10:$S$1048576, MATCH(AC411, $V$10:$V$1048576, 0)) -> 0 | AE411: =Z411 -> 0
M412: =IF(ISBLANK(D412), "", IFERROR(PROPER(TEXT(D412,"mmmm")),"")) | N412: =IF(H412="","",H412) | O412: =IFERROR(RIGHT(N412,LEN(N412)-SEARCH("- ",N412)-1),"") | R412: =COUNTIF($O:$O,Q412) -> 0 | S412: =Q412 -> 0 | U412: =COUNTIF(R$10:R412,R412) -> 395 | V412: =R412&U412 -> 0395 | W412: =INDEX($S$10:$S$401, MATCH(V412,$V$10:$V$1048576, 0)) -> #REF! | Y412: 403 | Z412: =LARGE($R$10:$R$1048576,Y412) -> 0 | AA412: =INDEX(S$10:S$1000, MATCH(R412, R$10:R$1000, 0)) -> Guarda-móveis | AB412: =COUNTIF(R$10:R412,R412) -> 395 | AC412: =R412&U412 -> 0395 | AD412: =INDEX($S$10:$S$1048576, MATCH(AC412, $V$10:$V$1048576, 0)) -> 0 | AE412: =Z412 -> 0
... M550: =IF(ISBLANK(D550), "", IFERROR(PROPER(TEXT(D550,"mmmm")),"")) | N550: =IF(H550="","",H550) | O550: =IFERROR(RIGHT(N550,LEN(N550)-SEARCH("- ",N550)-1),"") | R550: =COUNTIF($O:$O,Q550) -> 0 | S550: =Q550 -> 0 | U550: =COUNTIF(R$10:R550,R550) -> 533 | V550: =R550&U550 -> 0533 | W550: =INDEX($S$10:$S$401, MATCH(V550,$V$10:$V$1048576, 0)) -> #REF! | Y550: 541 | Z550: =LARGE($R$10:$R$1048576,Y550) -> 0 | AA550: =INDEX(S$10:S$1000, MATCH(R550, R$10:R$1000, 0)) -> Guarda-móveis | AB550: =COUNTIF(R$10:R550,R550) -> 533 | AC550: =R550&U550 -> 0533 | AD550: =INDEX($S$10:$S$1048576, MATCH(AC550, $V$10:$V$1048576, 0)) -> 0 | AE550: =Z550 -> 0
AC551: =R551&U551 | AE551: =Z551 -> 0

Sheet ANÁLISE SERASA
A1: ANÁLISE DE CRÉDITO
B5: DECISÃO NA ANÁLISE DE CRÉDITO | C5: =_xlfn.IFS(B25="REPROVADO","REPROVADO",B44="REPROVADO","REPROVADO",B53="REPROVADO","REPROVADO",B34="REPROVADO","REPROVADO",B58="REPROVADO","REPROVADO",B68="RISCO ALTO","REPROVADO",B68="RISCO MÉDIO","ANÁLISE DA DIRETORIA",B68="BAIXO RISCO","APROVADO") -> REPROVADO
B7: LIBERAÇÃO DO FINANCEIRO | C7: EM ANÁLISE
B9: SOLICITAÇÃO
B11: DATA DE ANÁLISE | C11: =TODAY() -> 45738
B12: SETOR/ SOLICITANTE | C12: Departamento de Crédito/Análise de Crédito
B13: OBSERVAÇÃO | C13: Potencial Cliente do Segmento Agronegócio
E14: Critérios
B15: DADOS CADASTRAIS DA EMPRESA
B17: CNPJ /CPF | C17: 00.111.222/0001-00 | E17: -
B18: DATA ABERTURA | C18: 43831 | E18: =IF(ISBLANK(C18),"",IF(TODAY()-C18>=5*365,"APROVADO","REPROVADO")) -> APROVADO
B19: NOME EMPRESARIAL | C19: Artigos de Radioterapia | E19: -
B20: CÓDIGO E DESCRIÇÃO DA ATIVIDADE ECONÔMICA PRINCIPAL | C20: 161-0/03 - Serviço de preparação de terreno, cultivo e colheita | E20: -
B21: CÓDIGO E DESCRIÇÃO DA NATUREZA JURÍDICA | C21: 206-2 | E21: =IF(VLOOKUP(C21,'Tabela de Natureza Jurídica '!A:C,3,0)="Entidades empresariais","APROVADO","REPROVADO") -> APROVADO
B22: ENDEREÇO ELETRÔNICO | C22: teste@teste.com.br | E22: =IF(ISBLANK(C22),"","APROVADO") -> APROVADO
B23: DOMINIO EMPRESARIAL | C23: Sim | E23: =IF(C23="SIM","APROVADO",IF(C23="NÃO","REPROVADO","")) -> APROVADO
B24: SITUAÇÃO CADASTRAL | C24: Ativa | E24: =IF(C24="ATIVA","APROVADO",IF(C23="NÃO","REPROVADO","")) -> APROVADO
B25: =IF(OR(E18="",E21="",E22="",E23="",E24=""),"",IF(OR(E18="REPROVADO",E21="REPROVADO",E22="REPROVADO",E23="REPROVADO",E24="REPROVADO"),"REPROVADO","ANALISAR SERASA")) -> ANALISAR SERASA | E25: -
B27: PENDÊNCIAS (INTERNA) E LIMITE DE INADIMPLÊNCIA
B29: CONTAS A RECEBER PENDENTES (A Vencer) | C29: Sim | E29: -
B30: COTAS A RECEBER EM ATRASO | C30: Não | E30: =IF(C30="SIM","REPROVADO",IF(C30="NÃO","APROVADO","")) -> APROVADO
B31: LIMITE DE INADIMPLÊNCIA EM VALOR | C31: 0 | E31: =IF(C31=0,"APROVADO",IF(C31>1000,"REPROVADO","ANALISAR PENDÊNCIA")) -> APROVADO
B32: DIAS EM ATRASO | C32: 0 | D32: =IF(C32=1, "Venceu! Faz 1 dia, atenção leve", IF(C32=2, "Venceu!Faz 2 dias, atenção moderada", IF(C32=3, "Venceu! Faz 3 dias, atenção urgente", IF(C32>3, "Venceu! Faz "&C32&" dias, por gentileza verificar!", "Em dia!!!")))) -> Em dia!!! | E32: =IF(C32>0,"REPROVADO",IF(C32=0,"APROVADO")) -> APROVADO
B33: CONTAS A RECEBER COM + DE 30 DIAS EM ATRASO | C33: 0 | D33: =IF(C33>30, "Atenção Imediata, Elegibilidade para Negativação:", "Dentro do prazo!!!") -> Dentro do prazo!!! | E33: =IF(C33=0, "APROVADO", "REPROVADO") -> APROVADO
B34: =IF(OR(E30="REPROVADO",E31="REPROVADO",E32="REPROVADO",E33="REPROVADO"),"REPROVADO","APROVADO") -> APROVADO | E34: -
B36: SERASA
B38: PENDÊNCIAS FINANCEIRAS | C38: Não | E38: =IF(ISBLANK(C38),"",IF(C38="NÃO","LIBERADO","REPROVADO")) -> LIBERADO
B39: PROTESTOS | C39: Não | E39: =IF(ISBLANK(C39),"",IF(C39="NÃO","LIBERADO","REPROVADO")) -> LIBERADO
B40: CHEQUES SEM FUNDO | C40: Não | E40: =IF(ISBLANK(C40),"",IF(C40="NÃO","LIBERADO","REPROVADO")) -> LIBERADO
B41: AÇÕES JUDICIAIS | C41: Não | E41: =IF(ISBLANK(C41),"",IF(C41="NÃO","LIBERADO","REPROVADO")) -> LIBERADO
B42: PARTICIPAÇÃO EM FALÊNCIAS | C42: Não | E42: =IF(ISBLANK(C42),"",IF(C42="NÃO","LIBERADO","REPROVADO")) -> LIBERADO
B43: FALÊNCIA/CONCORDARA/RECUPERAÇÃO JUDICIAL | C43: Não | E43: =IF(ISBLANK(C43),"",IF(C43="NÃO","LIBERADO","REPROVADO")) -> LIBERADO
B44: =IF(SUMPRODUCT((E38:E43="REPROVADO")*1)>0,"ANALISAR PENDÊNCIA",IF(SUMPRODUCT((E38:E43="LIBERADO")*1)>0,"ANALISAR RISCO","")) -> ANALISAR RISCO | E44: -
B46: DETALHAMENTO DAS PÊNDENCIAS
B48: VALOR TOTAL | C48: 0 | E48: =IF((C48/C67)<1%,"LIBERADO","REPROVADO") -> LIBERADO
B49: QUANTIDADE | C49: 0 | E49: =IF(C49<=3,"LIBERADO","REPROVADO") -> LIBERADO
B50: DATA DA INCLUSÃO | C50: 0 | E50: -
B51: SEGMENTO DA INCLUSÃO | C51: TELEFONIA | E51: =IF(C51="LOJA","REPROVADO","LIBERADO") -> LIBERADO
B52: NO CASO DE OUTROS DESCREVER | E52: -
B53: =IF(OR(E48="REPROVADO",E49="REPROVADO",E51="REPROVADO"),"REPROVADO","ANALISAR RISCO") -> ANALISAR RISCO | E53: -
B55: ANALISE DE RISCO
B57: SCORE | C57: =100+800/2 -> 500 | E57: =IF(C57<>0,"LIBERADO","REPROVADO") -> LIBERADO
B58: =IF(E57="REPROVADO","REPROVADO",IF(E57="Liberado","ANALISAR RISCO","")) -> ANALISAR RISCO | E58: -
B60: PARECER SCORE
B62: SCORE SÓCIOS | C62: 500 | E62: =C62*20/1000 -> 10
B63: PROBABILIDADE DE INADIMPLÊNCIA | C63: 0.0162 | E63: -
B64: RISCO DE CRÉDITO | C64: Médio | E64: =_xlfn.IFS(C64="Mínimo","40",C64="Baixo","30",C64="Médio","20",C64="Relevante","10",C64="Iminente","0") -> 20
B65: PONTUALIDADE DE PAGAMENTO INDICADOR | C65: 0 | E65: -
B66: PONTUALIDADE DE PAGAMENTO STATUS | C66: Baixa | E66: =_xlfn.IFS(C66="Alta","40",C66="Média","30",C66="Baixa","15",C66="Miníma","0",C66="Sem Cadastro","0") -> 15
B67: FATURAMENTO MENSAL | C67: =2000000/12 -> 166666.67 | E67: =(E62+E64+E66)/100 -> 0.45
B68: =IF(E67>80%,"BAIXO RISCO",IF(E67<50%,"RISCO ALTO","RISCO MÉDIO")) -> RISCO ALTO
B70: CONDIÇÕES DA LIBERAÇÃO
B72: PERIODICIDADE DO FATURAMENTO | C72: NÃO SE APLICA
B73: PRAZO DE PAGTO EM DIAS | C73: 0
B74: LIMITE DE FATURAMENTO MENSAL | C74: =C67*1% -> 1666.6667
B75: OUTRAS CONDIÇÕES

Sheet RELATÓRIO DE CONSULTAS - SERASA
A1: RELATÓRIO DE CONSULTAS - SERASA
C5: Janeiro | D5: Fevereiro | E5: Março | F5: Abril | G5: Maio | H5: Junho | I5: Julho | J5: Agosto | K5: Setembro | L5: Outubro | M5: Novembro | N5: Dezembro | O5: TOTAL | Q5: Média de consultas Anual
B6: ME (Microempresa) | C6: =COUNTIFS('CONTROLE DIÁRIO DE CONSULTAS'!$G$10:$G$1048576,$B$6,'CONTROLE DIÁRIO DE CONSULTAS'!$M$10:$M$1048576, C5) -> 1 | D6: =COUNTIFS('CONTROLE DIÁRIO DE CONSULTAS'!$G$10:$G$1048576,'RELATÓRIO DE CONSULTAS - SERASA'!$B$6,'CONTROLE DIÁRIO DE CONSULTAS'!$M$10:$M$1048576, D5) -> 0 | E6: =COUNTIFS('CONTROLE DIÁRIO DE CONSULTAS'!$G$10:$G$1048576,'RELATÓRIO DE CONSULTAS - SERASA'!$B$6,'CONTROLE DIÁRIO DE CONSULTAS'!$M$10:$M$1048576, E5) -> 0 | F6: =COUNTIFS('CONTROLE DIÁRIO DE CONSULTAS'!$G$10:$G$1048576,'RELATÓRIO DE CONSULTAS - SERASA'!$B$6,'CONTROLE DIÁRIO DE CONSULTAS'!$M$10:$M$1048576, F5) -> 0 | G6: =COUNTIFS('CONTROLE DIÁRIO DE CONSULTAS'!$G$10:$G$1048576,'RELATÓRIO DE CONSULTAS - SERASA'!$B$6,'CONTROLE DIÁRIO DE CONSULTAS'!$M$10:$M$1048576, G5) -> 0 | H6: =COUNTIFS('CONTROLE DIÁRIO DE CONSULTAS'!$G$10:$G$1048576,'RELATÓRIO DE CONSULTAS - SERASA'!$B$6,'CONTROLE DIÁRIO DE CONSULTAS'!$M$10:$M$1048576, H5) -> 0 | I6: =COUNTIFS('CONTROLE DIÁRIO DE CONSULTAS'!$G$10:$G$1048576,'RELATÓRIO DE CONSULTAS - SERASA'!$B$6,'CONTROLE DIÁRIO DE CONSULTAS'!$M$10:$M$1048576, I5) -> 0 | J6: =COUNTIFS('CONTROLE DIÁRIO DE CONSULTAS'!$G$10:$G$1048576,'RELATÓRIO DE CONSULTAS - SERASA'!$B$6,'CONTROLE DIÁRIO DE CONSULTAS'!$M$10:$M$1048576, J5) -> 0 | K6: =COUNTIFS('CONTROLE DIÁRIO DE CONSULTAS'!$G$10:$G$1048576,'RELATÓRIO DE CONSULTAS - SERASA'!$B$6,'CONTROLE DIÁRIO DE CONSULTAS'!$M$10:$M$1048576, K5) -> 0 | ... N6: =COUNTIFS('CONTROLE DIÁRIO DE CONSULTAS'!$G$10:$G$1048576,'RELATÓRIO DE CONSULTAS - SERASA'!$B$6,'CONTROLE DIÁRIO DE CONSULTAS'!$M$10:$M$1048576, N5) -> 0 | O6: =SUM($C$6:$N$6) -> 1 | Q6: =AVERAGE($O$13/12) -> 2.1666667
B7: MEI (Microempreendedor Individual) | C7: =COUNTIFS('CONTROLE DIÁRIO DE CONSULTAS'!$G$10:$G$1048576,$B$7,'CONTROLE DIÁRIO DE CONSULTAS'!$M$10:$M$1048576, C5) -> 0 | D7: =COUNTIFS('CONTROLE DIÁRIO DE CONSULTAS'!$G$10:$G$1048576,$B$7,'CONTROLE DIÁRIO DE CONSULTAS'!$M$10:$M$1048576, D5) -> 5 | E7: =COUNTIFS('CONTROLE DIÁRIO DE CONSULTAS'!$G$10:$G$1048576,$B$7,'CONTROLE DIÁRIO DE CONSULTAS'!$M$10:$M$1048576, E5) -> 0 | F7: =COUNTIFS('CONTROLE DIÁRIO DE CONSULTAS'!$G$10:$G$1048576,$B$7,'CONTROLE DIÁRIO DE CONSULTAS'!$M$10:$M$1048576, F5) -> 0 | G7: =COUNTIFS('CONTROLE DIÁRIO DE CONSULTAS'!$G$10:$G$1048576,$B$7,'CONTROLE DIÁRIO DE CONSULTAS'!$M$10:$M$1048576, G5) -> 0 | H7: =COUNTIFS('CONTROLE DIÁRIO DE CONSULTAS'!$G$10:$G$1048576,$B$7,'CONTROLE DIÁRIO DE CONSULTAS'!$M$10:$M$1048576, H5) -> 0 | I7: =COUNTIFS('CONTROLE DIÁRIO DE CONSULTAS'!$G$10:$G$1048576,$B$7,'CONTROLE DIÁRIO DE CONSULTAS'!$M$10:$M$1048576, I5) -> 0 | J7: =COUNTIFS('CONTROLE DIÁRIO DE CONSULTAS'!$G$10:$G$1048576,$B$7,'CONTROLE DIÁRIO DE CONSULTAS'!$M$10:$M$1048576, J5) -> 0 | ... N7: =COUNTIFS('CONTROLE DIÁRIO DE CONSULTAS'!$G$10:$G$1048576,$B$7,'CONTROLE DIÁRIO DE CONSULTAS'!$M$10:$M$1048576, N5) -> 0 | O7: =SUM($C$7:$N$7) -> 5 | Q7: =AVERAGE($O$13/12) -> 2.1666667
B8: EPP (Empresa de Pequeno Porte) | C8: =COUNTIFS('CONTROLE DIÁRIO DE CONSULTAS'!$G$10:$G$1048576,$B$8,'CONTROLE DIÁRIO DE CONSULTAS'!$M$10:$M$1048576, C5) -> 1 | D8: =COUNTIFS('CONTROLE DIÁRIO DE CONSULTAS'!$G$10:$G$1048576,$B$8,'CONTROLE DIÁRIO DE CONSULTAS'!$M$10:$M$1048576, D5) -> 0 | E8: =COUNTIFS('CONTROLE DIÁRIO DE CONSULTAS'!$G$10:$G$1048576,$B$8,'CONTROLE DIÁRIO DE CONSULTAS'!$M$10:$M$1048576, E5) -> 2 | F8: =COUNTIFS('CONTROLE DIÁRIO DE CONSULTAS'!$G$10:$G$1048576,$B$8,'CONTROLE DIÁRIO DE CONSULTAS'!$M$10:$M$1048576, F5) -> 2 | G8: =COUNTIFS('CONTROLE DIÁRIO DE CONSULTAS'!$G$10:$G$1048576,$B$8,'CONTROLE DIÁRIO DE CONSULTAS'!$M$10:$M$1048576, G5) -> 0 | H8: =COUNTIFS('CONTROLE DIÁRIO DE CONSULTAS'!$G$10:$G$1048576,$B$8,'CONTROLE DIÁRIO DE CONSULTAS'!$M$10:$M$1048576, H5) -> 2 | I8: =COUNTIFS('CONTROLE DIÁRIO DE CONSULTAS'!$G$10:$G$1048576,$B$8,'CONTROLE DIÁRIO DE CONSULTAS'!$M$10:$M$1048576, I5) -> 2 | J8: =COUNTIFS('CONTROLE DIÁRIO DE CONSULTAS'!$G$10:$G$1048576,$B$8,'CONTROLE DIÁRIO DE CONSULTAS'!$M$10:$M$1048576, J5) -> 0 | ... N8: =COUNTIFS('CONTROLE DIÁRIO DE CONSULTAS'!$G$10:$G$1048576,$B$8,'CONTROLE DIÁRIO DE CONSULTAS'!$M$10:$M$1048576, N5) -> 0 | O8: =SUM(C8:N8) -> 9 | Q8: =AVERAGE($O$13/12) -> 2.1666667
B9: LTDA (Sociedade Limitada) | C9: =COUNTIFS('CONTROLE DIÁRIO DE CONSULTAS'!$G$10:$G$1048576,$B$9,'CONTROLE DIÁRIO DE CONSULTAS'!$M$10:$M$1048576, C5) -> 0 | D9: =COUNTIFS('CONTROLE DIÁRIO DE CONSULTAS'!$G$10:$G$1048576,$B$9,'CONTROLE DIÁRIO DE CONSULTAS'!$M$10:$M$1048576, D5) -> 0 | E9: =COUNTIFS('CONTROLE DIÁRIO DE CONSULTAS'!$G$10:$G$1048576,$B$9,'CONTROLE DIÁRIO DE CONSULTAS'!$M$10:$M$1048576, E5) -> 0 | F9: =COUNTIFS('CONTROLE DIÁRIO DE CONSULTAS'!$G$10:$G$1048576,$B$9,'CONTROLE DIÁRIO DE CONSULTAS'!$M$10:$M$1048576, F5) -> 0 | G9: =COUNTIFS('CONTROLE DIÁRIO DE CONSULTAS'!$G$10:$G$1048576,$B$9,'CONTROLE DIÁRIO DE CONSULTAS'!$M$10:$M$1048576, G5) -> 4 | H9: =COUNTIFS('CONTROLE DIÁRIO DE CONSULTAS'!$G$10:$G$1048576,$B$9,'CONTROLE DIÁRIO DE CONSULTAS'!$M$10:$M$1048576, H5) -> 0 | I9: =COUNTIFS('CONTROLE DIÁRIO DE CONSULTAS'!$G$10:$G$1048576,$B$9,'CONTROLE DIÁRIO DE CONSULTAS'!$M$10:$M$1048576, I5) -> 0 | J9: =COUNTIFS('CONTROLE DIÁRIO DE CONSULTAS'!$G$10:$G$1048576,$B$9,'CONTROLE DIÁRIO DE CONSULTAS'!$M$10:$M$1048576, J5) -> 0 | ... N9: =COUNTIFS('CONTROLE DIÁRIO DE CONSULTAS'!$G$10:$G$1048576,$B$9,'CONTROLE DIÁRIO DE CONSULTAS'!$M$10:$M$1048576, N5) -> 0 | O9: =SUM(C9:N9) -> 5 | Q9: =AVERAGE($O$13/12) -> 2.1666667
B10: S/A (Sociedade Anônima) | C10: =COUNTIFS('CONTROLE DIÁRIO DE CONSULTAS'!G10:G1048576,$B$10,'CONTROLE DIÁRIO DE CONSULTAS'!$M$10:$M$1048576, C5) -> 2 | D10: =COUNTIFS('CONTROLE DIÁRIO DE CONSULTAS'!$G$10:$G$1048576,$B$10,'CONTROLE DIÁRIO DE CONSULTAS'!$M$10:$M$1048576, D5) -> 0 | E10: =COUNTIFS('CONTROLE DIÁRIO DE CONSULTAS'!$G$10:$G$1048576,$B$10,'CONTROLE DIÁRIO DE CONSULTAS'!$M$10:$M$1048576, E5) -> 0 | F10: =COUNTIFS('CONTROLE DIÁRIO DE CONSULTAS'!$G$10:$G$1048576,$B$10,'CONTROLE DIÁRIO DE CONSULTAS'!$M$10:$M$1048576, F5) -> 0 | G10: =COUNTIFS('CONTROLE DIÁRIO DE CONSULTAS'!$G$10:$G$1048576,$B$10,'CONTROLE DIÁRIO DE CONSULTAS'!$M$10:$M$1048576, G5) -> 0 | H10: =COUNTIFS('CONTROLE DIÁRIO DE CONSULTAS'!$G$10:$G$1048576,$B$10,'CONTROLE DIÁRIO DE CONSULTAS'!$M$10:$M$1048576, H5) -> 0 | I10: =COUNTIFS('CONTROLE DIÁRIO DE CONSULTAS'!$G$10:$G$1048576,$B$10,'CONTROLE DIÁRIO DE CONSULTAS'!$M$10:$M$1048576, I5) -> 0 | J10: =COUNTIFS('CONTROLE DIÁRIO DE CONSULTAS'!$G$10:$G$1048576,$B$10,'CONTROLE DIÁRIO DE CONSULTAS'!$M$10:$M$1048576, J5) -> 0 | K10: =COUNTIFS('CONTROLE DIÁRIO DE CONSULTAS'!$G$10:$G$1048576,$B$10,'CONTROLE DIÁRIO DE CONSULTAS'!$M$10:$M$1048576, K5) -> 0 | ... N10: =COUNTIFS('CONTROLE DIÁRIO DE CONSULTAS'!$G$10:$G$1048576,$B$10,'CONTROLE DIÁRIO DE CONSULTAS'!$M$10:$M$1048576, N5) -> 0 | O10: =SUM(C10:N10) -> 2 | Q10: =AVERAGE($O$13/12) -> 2.1666667
B11: Sociedade Anônima | C11: =COUNTIFS('CONTROLE DIÁRIO DE CONSULTAS'!$G$10:$G$1048576,$B$11,'CONTROLE DIÁRIO DE CONSULTAS'!$M$10:$M$1048576, C5) -> 0 | D11: =COUNTIFS('CONTROLE DIÁRIO DE CONSULTAS'!$G$10:$G$1048576,$B$11,'CONTROLE DIÁRIO DE CONSULTAS'!$M$10:$M$1048576, D5) -> 0 | E11: =COUNTIFS('CONTROLE DIÁRIO DE CONSULTAS'!$G$10:$G$1048576,$B$11,'CONTROLE DIÁRIO DE CONSULTAS'!$M$10:$M$1048576, E5) -> 0 | F11: =COUNTIFS('CONTROLE DIÁRIO DE CONSULTAS'!$G$10:$G$1048576,$B$11,'CONTROLE DIÁRIO DE CONSULTAS'!$M$10:$M$1048576, F5) -> 0 | G11: =COUNTIFS('CONTROLE DIÁRIO DE CONSULTAS'!$G$10:$G$1048576,$B$11,'CONTROLE DIÁRIO DE CONSULTAS'!$M$10:$M$1048576, G5) -> 0 | H11: =COUNTIFS('CONTROLE DIÁRIO DE CONSULTAS'!$G$10:$G$1048576,$B$11,'CONTROLE DIÁRIO DE CONSULTAS'!$M$10:$M$1048576, H5) -> 0 | I11: =COUNTIFS('CONTROLE DIÁRIO DE CONSULTAS'!$G$10:$G$1048576,$B$11,'CONTROLE DIÁRIO DE CONSULTAS'!$M$10:$M$1048576, I5) -> 0 | J11: =COUNTIFS('CONTROLE DIÁRIO DE CONSULTAS'!$G$10:$G$1048576,$B$11,'CONTROLE DIÁRIO DE CONSULTAS'!$M$10:$M$1048576, J5) -> 0 | ... N11: =COUNTIFS('CONTROLE DIÁRIO DE CONSULTAS'!$G$10:$G$1048576,$B$11,'CONTROLE DIÁRIO DE CONSULTAS'!$M$10:$M$1048576, N5) -> 0 | O11: =SUM(C11:N11) -> 0 | Q11: =AVERAGE($O$13/12) -> 2.1666667
B12: PF (Pessoa Física) | C12: =COUNTIFS('CONTROLE DIÁRIO DE CONSULTAS'!$G$10:$G$1048576,$B$12,'CONTROLE DIÁRIO DE CONSULTAS'!$M$10:$M$1048576, C5) -> 0 | D12: =COUNTIFS('CONTROLE DIÁRIO DE CONSULTAS'!$G$10:$G$1048576,$B$12,'CONTROLE DIÁRIO DE CONSULTAS'!$M$10:$M$1048576, D5) -> 0 | E12: =COUNTIFS('CONTROLE DIÁRIO DE CONSULTAS'!$G$10:$G$1048576,$B$12,'CONTROLE DIÁRIO DE CONSULTAS'!$M$10:$M$1048576, E5) -> 0 | F12: =COUNTIFS('CONTROLE DIÁRIO DE CONSULTAS'!$G$10:$G$1048576,$B$12,'CONTROLE DIÁRIO DE CONSULTAS'!$M$10:$M$1048576, F5) -> 0 | G12: =COUNTIFS('CONTROLE DIÁRIO DE CONSULTAS'!$G$10:$G$1048576,$B$12,'CONTROLE DIÁRIO DE CONSULTAS'!$M$10:$M$1048576, G5) -> 0 | H12: =COUNTIFS('CONTROLE DIÁRIO DE CONSULTAS'!$G$10:$G$1048576,$B$12,'CONTROLE DIÁRIO DE CONSULTAS'!$M$10:$M$1048576, H5) -> 0 | I12: =COUNTIFS('CONTROLE DIÁRIO DE CONSULTAS'!$G$10:$G$1048576,$B$12,'CONTROLE DIÁRIO DE CONSULTAS'!$M$10:$M$1048576, I5) -> 0 | J12: =COUNTIFS('CONTROLE DIÁRIO DE CONSULTAS'!$G$10:$G$1048576,$B$12,'CONTROLE DIÁRIO DE CONSULTAS'!$M$10:$M$1048576, J5) -> 0 | ... N12: =COUNTIFS('CONTROLE DIÁRIO DE CONSULTAS'!$G$10:$G$1048576,$B$12,'CONTROLE DIÁRIO DE CONSULTAS'!$M$10:$M$1048576, N5) -> 0 | O12: =SUM(C12:N12) -> 0 | Q12: =AVERAGE($O$13/12) -> 2.1666667
B13: Quantidade de Consultas no Serasa | C13: =COUNTIF('CONTROLE DIÁRIO DE CONSULTAS'!$M$10:$M$40,C5) -> 4 | D13: =COUNTIF('CONTROLE DIÁRIO DE CONSULTAS'!$M$10:$M$40,D5) -> 5 | E13: =COUNTIF('CONTROLE DIÁRIO DE CONSULTAS'!$M$10:$M$40,E5) -> 2 | F13: =COUNTIF('CONTROLE DIÁRIO DE CONSULTAS'!$M$10:$M$40,F5) -> 2 | G13: =COUNTIF('CONTROLE DIÁRIO DE CONSULTAS'!$M$10:$M$40,G5) -> 4 | H13: =COUNTIF('CONTROLE DIÁRIO DE CONSULTAS'!$M$10:$M$40,H5) -> 2 | I13: =COUNTIF('CONTROLE DIÁRIO DE CONSULTAS'!$M$10:$M$40,I5) -> 2 | J13: =COUNTIF('CONTROLE DIÁRIO DE CONSULTAS'!$M$10:$M$40,J5) -> 2 | ... N13: =COUNTIF('CONTROLE DIÁRIO DE CONSULTAS'!$M$10:$M$40,N5) -> 0 | O13: =SUM(C13:N13) -> 26 | Q13: =AVERAGE($O$13/12) -> 2.1666667
Q14: =AVERAGE($O$13/12) -> 2.1666667
Q15: =AVERAGE($O$13/12) -> 2.1666667
Q16: =AVERAGE($O$13/12) -> 2.1666667
Q17: =AVERAGE($O$13/12) -> 2.1666667

Sheet GRÁFICO
